[
   {
      "title": "ооо \"ртк\"",
      "link": "/id/6108857",
      "head_title": "конкурсный управляющий",
      "head_name": "смирнов андрей михайлович",
      "inn": "5403338560",
      "ogrn": "1125476094578",
      "reg_date": "14 июня 2012 г.",
      "reg_cap": "1 000 000 руб.",
      "status": null,
      "main_activity": "47.11 торговля розничная преимущественно пищевыми продуктами, включая напитки, и табачными изделиями в неспециализированных магазинах",
      "main_activity_code": 471100,
      "address": "630088, новосибирская область, город новосибирск, улица петухова, 29"
   },
   {
      "title": "ооо \"приуральское\"",
      "link": "/id/6982674",
      "head_title": "ликвидатор",
      "head_name": "артеева лариса васильевна",
      "inn": "1105022885",
      "ogrn": "1131105000487",
      "reg_date": "10 сентября 2013 г.",
      "reg_cap": "10 000 руб.",
      "status": "организация в процессе ликвидации",
      "main_activity": "47.11 торговля розничная преимущественно пищевыми продуктами, включая напитки, и табачными изделиями в неспециализированных магазинах",
      "main_activity_code": 471100,
      "address": "169625, республика коми, город печора, село приуральское, лесная улица, 6"
   },
   {
      "title": "ооо тк \"новоторг\"",
      "link": "/id/6928272",
      "head_title": "управляющий - индивидуальный предприниматель",
      "head_name": "верещагина наталья валерьевна",
      "inn": "2724179860",
      "ogrn": "1132724008284",
      "reg_date": "22 июля 2013 г.",
      "reg_cap": "105 000 руб.",
      "status": null,
      "main_activity": "47.11 торговля розничная преимущественно пищевыми продуктами, включая напитки, и табачными изделиями в неспециализированных магазинах",
      "main_activity_code": 471100,
      "address": "680000, хабаровский край, город хабаровск, московская улица, дом 4, помещение 2"
   },
   {
      "title": "ооо \"биг фуд\"",
      "link": "/id/10149362",
      "head_title": "директор",
      "head_name": "перевощиков олег михайлович",
      "inn": "4345366910",
      "ogrn": "1134345021326",
      "reg_date": "16 сентября 2013 г.",
      "reg_cap": "10 000 руб.",
      "status": null,
      "main_activity": "47.11 торговля розничная преимущественно пищевыми продуктами, включая напитки, и табачными изделиями в неспециализированных магазинах",
      "main_activity_code": 471100,
      "address": "610002, кировская область, город киров, улица ленина, дом 93 этаж 1, помещение 1004"
   },
   {
      "title": "ооо \"триа-групп\"",
      "link": "/id/7091871",
      "head_title": "директор",
      "head_name": "антонов алексей александрович",
      "inn": "5261087781",
      "ogrn": "1135261003745",
      "reg_date": "21 октября 2013 г.",
      "reg_cap": "510 000 руб.",
      "status": null,
      "main_activity": "47.11 торговля розничная преимущественно пищевыми продуктами, включая напитки, и табачными изделиями в неспециализированных магазинах",
      "main_activity_code": 471100,
      "address": "603162, нижегородская область, город нижний новгород, улица академика сахарова, 111, п4"
   },
   {
      "title": "ооо \"мд трейд\"",
      "link": "/id/7300194",
      "head_title": "директор",
      "head_name": "федотов максим юрьевич",
      "inn": "7455017184",
      "ogrn": "1147456002616",
      "reg_date": "10 апреля 2014 г.",
      "reg_cap": "30 000 руб.",
      "status": null,
      "main_activity": "47.11 торговля розничная преимущественно пищевыми продуктами, включая напитки, и табачными изделиями в неспециализированных магазинах",
      "main_activity_code": 471100,
      "address": "457395, челябинская область, карталинский район, поселок джабык, улица мира, дом 83а, помещение 1"
   },
   {
      "title": "ооо \"бп\"",
      "link": "/id/7814755",
      "head_title": "генеральный директор",
      "head_name": "безносова ольга александровна",
      "inn": "1108023238",
      "ogrn": "1151101006980",
      "reg_date": "26 августа 2015 г.",
      "reg_cap": "11 000 руб.",
      "status": null,
      "main_activity": "47.11 торговля розничная преимущественно пищевыми продуктами, включая напитки, и табачными изделиями в неспециализированных магазинах",
      "main_activity_code": 471100,
      "address": "169501, республика коми, город сосногорск, улица маяковского, дом 3, квартира 44"
   },
   {
      "title": "ооо \"новоторг сервис\"",
      "link": "/id/7658712",
      "head_title": "управляющий - индивидуальный предприниматель",
      "head_name": "верещагина наталья валерьевна",
      "inn": "2724201900",
      "ogrn": "1152724003761",
      "reg_date": "26 мая 2015 г.",
      "reg_cap": "50 000 руб.",
      "status": null,
      "main_activity": "47.11 торговля розничная преимущественно пищевыми продуктами, включая напитки, и табачными изделиями в неспециализированных магазинах",
      "main_activity_code": 471100,
      "address": "680032, хабаровский край, город хабаровск, производственный переулок, дом 1 литер и, помещение 13"
   },
   {
      "title": "ооо иц \"новоторг\"",
      "link": "/id/7658713",
      "head_title": "управляющий - индивидуальный предприниматель",
      "head_name": "верещагина наталья валерьевна",
      "inn": "2724201883",
      "ogrn": "1152724003772",
      "reg_date": "26 мая 2015 г.",
      "reg_cap": "50 000 руб.",
      "status": null,
      "main_activity": "47.11 торговля розничная преимущественно пищевыми продуктами, включая напитки, и табачными изделиями в неспециализированных магазинах",
      "main_activity_code": 471100,
      "address": "680032, хабаровский край, город хабаровск, производственный переулок, дом 1 литер и, помещение 13"
   },
   {
      "title": "ооо \"св-торг\"",
      "link": "/id/10203593",
      "head_title": "генеральный директор",
      "head_name": "еровенко анжела владимировна",
      "inn": "2827009540",
      "ogrn": "1152801010240",
      "reg_date": "3 ноября 2015 г.",
      "reg_cap": "1 000 000 руб.",
      "status": null,
      "main_activity": "47.11 торговля розничная преимущественно пищевыми продуктами, включая напитки, и табачными изделиями в неспециализированных магазинах",
      "main_activity_code": 471100,
      "address": "676950, амурская область, тамбовский район, село тамбовка, ленинская улица, дом 73"
   },
   {
      "title": "ооо \"три'о\"",
      "link": "/id/7753536",
      "head_title": "генеральный директор",
      "head_name": "амбарян гор варужанович",
      "inn": "7203351423",
      "ogrn": "1157232027985",
      "reg_date": "28 июля 2015 г.",
      "reg_cap": "10 000 руб.",
      "status": null,
      "main_activity": "47.11 торговля розничная преимущественно пищевыми продуктами, включая напитки, и табачными изделиями в неспециализированных магазинах",
      "main_activity_code": 471100,
      "address": "625049, тюменская область, город тюмень, улица московский тракт, дом 141 корпус 2, квартира 14"
   },
   {
      "title": "ооо \"персонал-сити\"",
      "link": "/id/7685783",
      "head_title": "директор",
      "head_name": "серышева анна владимировна",
      "inn": "7610109114",
      "ogrn": "1157610001339",
      "reg_date": "16 марта 2015 г.",
      "reg_cap": "500 000 руб.",
      "status": null,
      "main_activity": "47.11 торговля розничная преимущественно пищевыми продуктами, включая напитки, и табачными изделиями в неспециализированных магазинах",
      "main_activity_code": 471100,
      "address": "152908, ярославская область, рыбинский район, город рыбинск, ярославский тракт, дом 71, офис 10"
   },
   {
      "title": "ооо \"неон\"",
      "link": "/id/7584966",
      "head_title": "генеральный директор",
      "head_name": "гезалов рагиб дайян оглы",
      "inn": "7714336104",
      "ogrn": "1157746334668",
      "reg_date": "10 апреля 2015 г.",
      "reg_cap": "20 000 руб.",
      "status": null,
      "main_activity": "47.11 торговля розничная преимущественно пищевыми продуктами, включая напитки, и табачными изделиями в неспециализированных магазинах",
      "main_activity_code": 471100,
      "address": "125414, город москва, петрозаводская улица, дом 24 корпус 2"
   },
   {
      "title": "ооо \"китоврас\"",
      "link": "/id/10478922",
      "head_title": "генеральный директор",
      "head_name": "сиротина елена александровна",
      "inn": "2509008670",
      "ogrn": "1162509050186",
      "reg_date": "17 мая 2016 г.",
      "reg_cap": "15 000 руб.",
      "status": null,
      "main_activity": "47.11 торговля розничная преимущественно пищевыми продуктами, включая напитки, и табачными изделиями в неспециализированных магазинах",
      "main_activity_code": 471100,
      "address": "692905, приморский край, город находка, гоголевский переулок, дом 27"
   },
   {
      "title": "ооо \"фортуна\"",
      "link": "/id/10626089",
      "head_title": "директор",
      "head_name": "кузницына лариса александровна",
      "inn": "3327134417",
      "ogrn": "1163328064900",
      "reg_date": "13 сентября 2016 г.",
      "reg_cap": "10 000 руб.",
      "status": null,
      "main_activity": "47.11 торговля розничная преимущественно пищевыми продуктами, включая напитки, и табачными изделиями в неспециализированных магазинах",
      "main_activity_code": 471100,
      "address": "600015, владимирская область, город владимир, улица чайковского, дом 12/22, помещение 2"
   },
   {
      "title": "пк \"харовский\"",
      "link": "/id/10537918",
      "head_title": "ликвидатор",
      "head_name": "смирнова наталья александровна",
      "inn": "3521006617",
      "ogrn": "1163525082467",
      "reg_date": "30 июня 2016 г.",
      "reg_cap": null,
      "status": "организация в процессе ликвидации",
      "main_activity": "47.11 торговля розничная преимущественно пищевыми продуктами, включая напитки, и табачными изделиями в неспециализированных магазинах",
      "main_activity_code": 471100,
      "address": "162250, вологодская область, харовский район, город харовск, октябрьская улица, дом 14, офис 1"
   },
   {
      "title": "ооо \"фп\"",
      "link": "/id/10522164",
      "head_title": "генеральный директор",
      "head_name": "воробьёв константин сергеевич",
      "inn": "7802584314",
      "ogrn": "1167847263022",
      "reg_date": "20 июня 2016 г.",
      "reg_cap": "10 000 руб.",
      "status": null,
      "main_activity": "47.11 торговля розничная преимущественно пищевыми продуктами, включая напитки, и табачными изделиями в неспециализированных магазинах",
      "main_activity_code": 471100,
      "address": "194017, город санкт-петербург, проспект тореза, дом 102 корпус 4 лит. а"
   },
   {
      "title": "ооо \"авалон трейд\"",
      "link": "/id/10766372",
      "head_title": "генеральный директор",
      "head_name": "демидов александр валерьевич",
      "inn": "7724389218",
      "ogrn": "5167746292600",
      "reg_date": "3 ноября 2016 г.",
      "reg_cap": "90 000 руб.",
      "status": null,
      "main_activity": "47.11 торговля розничная преимущественно пищевыми продуктами, включая напитки, и табачными изделиями в неспециализированных магазинах",
      "main_activity_code": 471100,
      "address": "115598, город москва, загорьевская улица, дом 17, квартира 12"
   },
   {
      "title": "ооо \"пельменный домик\"",
      "link": "/id/10823973",
      "head_title": "директор",
      "head_name": "шишова юлия вячеславовна",
      "inn": "3918013400",
      "ogrn": "1163926088336",
      "reg_date": "21 декабря 2016 г.",
      "reg_cap": "100 000 руб.",
      "status": null,
      "main_activity": "47.11 торговля розничная преимущественно пищевыми продуктами, включая напитки, и табачными изделиями в неспециализированных магазинах",
      "main_activity_code": 471100,
      "address": "238546, калининградская область, зеленоградский район, поселок холмогоровка, садовый переулок, дом 15а"
   },
   {
      "title": "ооо \"топ-маркет\"",
      "link": "/id/10990257",
      "head_title": "директор",
      "head_name": "резук андрей петрович",
      "inn": "2466181349",
      "ogrn": "1172468027489",
      "reg_date": "25 апреля 2017 г.",
      "reg_cap": "2 000 000 руб.",
      "status": null,
      "main_activity": "47.11 торговля розничная преимущественно пищевыми продуктами, включая напитки, и табачными изделиями в неспециализированных магазинах",
      "main_activity_code": 471100,
      "address": "660064, красноярский край, город красноярск, парусная улица, дом 10, помещение 247"
   },
   {
      "title": "ооо \"раму\"",
      "link": "/id/11046071",
      "head_title": "генеральный директор",
      "head_name": "таршхоева хава гирихановна",
      "inn": "0608045439",
      "ogrn": "1170608002586",
      "reg_date": "9 июня 2017 г.",
      "reg_cap": "10 000 руб.",
      "status": null,
      "main_activity": "47.11 торговля розничная преимущественно пищевыми продуктами, включая напитки, и табачными изделиями в неспециализированных магазинах",
      "main_activity_code": 471100,
      "address": "386150, республика ингушетия, назрановский район, село экажево, улица муталиева, дом 97"
   },
   {
      "title": "ооо \"агат\"",
      "link": "/id/11108624",
      "head_title": "директор",
      "head_name": "братанова светлана александровна",
      "inn": "4416004820",
      "ogrn": "1174401006340",
      "reg_date": "27 июля 2017 г.",
      "reg_cap": "500 000 руб.",
      "status": null,
      "main_activity": "47.11 торговля розничная преимущественно пищевыми продуктами, включая напитки, и табачными изделиями в неспециализированных магазинах",
      "main_activity_code": 471100,
      "address": "157460, костромская область, макарьевский район, город макарьев, дорожная улица, дом 43, квартира 2"
   },
   {
      "title": "ооо \"винторг-аэро\"",
      "link": "/id/11131102",
      "head_title": "генеральный директор",
      "head_name": "ковалевский виталий иванович",
      "inn": "9103085690",
      "ogrn": "1179102020239",
      "reg_date": "15 августа 2017 г.",
      "reg_cap": "100 000 руб.",
      "status": null,
      "main_activity": "47.11 торговля розничная преимущественно пищевыми продуктами, включая напитки, и табачными изделиями в неспециализированных магазинах",
      "main_activity_code": 471100,
      "address": "298500, республика крым, город алушта, улица ленина, дом 1"
   },
   {
      "title": "ооо \"галилео-7\"",
      "link": "/id/11262111",
      "head_title": "генеральный директор",
      "head_name": "велиев агиль адиль оглы",
      "inn": "7726418785",
      "ogrn": "5177746292279",
      "reg_date": "6 декабря 2017 г.",
      "reg_cap": "1 000 000 руб.",
      "status": null,
      "main_activity": "47.11 торговля розничная преимущественно пищевыми продуктами, включая напитки, и табачными изделиями в неспециализированных магазинах",
      "main_activity_code": 471100,
      "address": "117535, город москва, россошанский проезд, дом 6, эт 1 пом iii ком 7"
   },
   {
      "title": "ооо \"продуктовый дворик\"",
      "link": "/id/11443912",
      "head_title": "управляющий - индивидуальный предприниматель",
      "head_name": "верещагина наталья валерьевна",
      "inn": "2724228620",
      "ogrn": "1182724011381",
      "reg_date": "22 мая 2018 г.",
      "reg_cap": "50 000 руб.",
      "status": null,
      "main_activity": "47.11 торговля розничная преимущественно пищевыми продуктами, включая напитки, и табачными изделиями в неспециализированных магазинах",
      "main_activity_code": 471100,
      "address": "680009, хабаровский край, город хабаровск, почтовая улица, дом 51 литер д, помещение 37"
   },
   {
      "title": "ооо \"добротный продукт+\"",
      "link": "/id/11451027",
      "head_title": "ликвидатор",
      "head_name": "камалов ринат мухаматнурович",
      "inn": "0231009177",
      "ogrn": "1180280032338",
      "reg_date": "28 мая 2018 г.",
      "reg_cap": "10 000 руб.",
      "status": "организация в процессе ликвидации",
      "main_activity": "47.11 торговля розничная преимущественно пищевыми продуктами, включая напитки, и табачными изделиями в неспециализированных магазинах",
      "main_activity_code": 471100,
      "address": "452930, республика башкортостан, краснокамский район, село николо-березовка, садовая улица, дом 15"
   },
   {
      "title": "ооо \"урбан групп\"",
      "link": "/id/11514295",
      "head_title": "генеральный директор",
      "head_name": "убушаева мария владимировна",
      "inn": "9731007270",
      "ogrn": "1187746707279",
      "reg_date": "26 июля 2018 г.",
      "reg_cap": "20 000 руб.",
      "status": null,
      "main_activity": "47.11 торговля розничная преимущественно пищевыми продуктами, включая напитки, и табачными изделиями в неспециализированных магазинах",
      "main_activity_code": 471100,
      "address": "121609, город москва, осенняя улица, дом 23, э 9 пом i-957 к 34 оф 21"
   },
   {
      "title": "ооо \"купец\"",
      "link": "/id/11525851",
      "head_title": "генеральный директор",
      "head_name": "голованчук надежда андреевна",
      "inn": "6103017399",
      "ogrn": "1186196033396",
      "reg_date": "9 августа 2018 г.",
      "reg_cap": "10 000 руб.",
      "status": null,
      "main_activity": "47.11 торговля розничная преимущественно пищевыми продуктами, включая напитки, и табачными изделиями в неспециализированных магазинах",
      "main_activity_code": 471100,
      "address": "346623, ростовская область, багаевский район, хутор калинин, широкая улица, дом 98"
   },
   {
      "title": "ооо \"фермер\"",
      "link": "/id/11636719",
      "head_title": "генеральный директор",
      "head_name": "колчанов геннадий викторович",
      "inn": "7203463529",
      "ogrn": "1187232029390",
      "reg_date": "3 декабря 2018 г.",
      "reg_cap": "100 000 руб.",
      "status": null,
      "main_activity": "47.11 торговля розничная преимущественно пищевыми продуктами, включая напитки, и табачными изделиями в неспециализированных магазинах",
      "main_activity_code": 471100,
      "address": "625051, тюменская область, город тюмень, широтная улица, дом 104, помещение 11 офис 13а"
   },
   {
      "title": "ооо \"эра\"",
      "link": "/id/11671252",
      "head_title": "генеральный директор",
      "head_name": "шабалдо борис васильевич",
      "inn": "2983012885",
      "ogrn": "1192901000192",
      "reg_date": "14 января 2019 г.",
      "reg_cap": "500 000 руб.",
      "status": null,
      "main_activity": "47.11 торговля розничная преимущественно пищевыми продуктами, включая напитки, и табачными изделиями в неспециализированных магазинах",
      "main_activity_code": 471100,
      "address": "166730, ненецкий автономный округ, заполярный район, село нижняя пеша, улица калинина, дом 42, квартира 2"
   },
   {
      "title": "ооо \"подкова\"",
      "link": "/id/11676060",
      "head_title": "генеральный директор",
      "head_name": "аброськина наталия александровна",
      "inn": "7328100993",
      "ogrn": "1197325001752",
      "reg_date": "21 января 2019 г.",
      "reg_cap": "10 000 руб.",
      "status": null,
      "main_activity": "47.11 торговля розничная преимущественно пищевыми продуктами, включая напитки, и табачными изделиями в неспециализированных магазинах",
      "main_activity_code": 471100,
      "address": "432072, ульяновская область, город ульяновск, ульяновский проспект, дом 19, офис 116"
   },
   {
      "title": "ооо \"архимед\"",
      "link": "/id/11706823",
      "head_title": "генеральный директор",
      "head_name": "грачёва кристина олеговна",
      "inn": "9715338838",
      "ogrn": "1197746119867",
      "reg_date": "18 февраля 2019 г.",
      "reg_cap": "100 000 руб.",
      "status": null,
      "main_activity": "47.11 торговля розничная преимущественно пищевыми продуктами, включая напитки, и табачными изделиями в неспециализированных магазинах",
      "main_activity_code": 471100,
      "address": "127566, город москва, улица бестужевых, дом 4, квартира 5"
   },
   {
      "title": "ооо \"олимп\"",
      "link": "/id/11712481",
      "head_title": "директор",
      "head_name": "токбасиди ольга алексеевна",
      "inn": "0716012374",
      "ogrn": "1190726001311",
      "reg_date": "21 февраля 2019 г.",
      "reg_cap": "50 000 руб.",
      "status": null,
      "main_activity": "47.11 торговля розничная преимущественно пищевыми продуктами, включая напитки, и табачными изделиями в неспециализированных магазинах",
      "main_activity_code": 471100,
      "address": "361043, республика кабардино-балкарская, город прохладный, школьный переулок, дом 19/2"
   },
   {
      "title": "ооо \"фатима\"",
      "link": "/id/11717313",
      "head_title": "директор",
      "head_name": "межгихова фатимат харабиевна",
      "inn": "0701017387",
      "ogrn": "1190726001366",
      "reg_date": "26 февраля 2019 г.",
      "reg_cap": "50 000 руб.",
      "status": null,
      "main_activity": "47.11 торговля розничная преимущественно пищевыми продуктами, включая напитки, и табачными изделиями в неспециализированных магазинах",
      "main_activity_code": 471100,
      "address": "361522, республика кабардино-балкарская, баксанский район, село заюково, улица кирова, дом 207"
   },
   {
      "title": "ооо \"канцлер\"",
      "link": "/id/11738510",
      "head_title": "директор",
      "head_name": "широких юрий николаевич",
      "inn": "3666234906",
      "ogrn": "1193668011899",
      "reg_date": "19 марта 2019 г.",
      "reg_cap": "10 000 руб.",
      "status": null,
      "main_activity": "47.11 торговля розничная преимущественно пищевыми продуктами, включая напитки, и табачными изделиями в неспециализированных магазинах",
      "main_activity_code": 471100,
      "address": "394068, воронежская область, город воронеж, олимпийский бульвар, дом 14 неж.пом 12/1, офис 23"
   },
   {
      "title": "ооо \"южуралторг\"",
      "link": "/id/11752973",
      "head_title": "директор",
      "head_name": "силютин александр андреевич",
      "inn": "7452150540",
      "ogrn": "1197456016350",
      "reg_date": "3 апреля 2019 г.",
      "reg_cap": "10 000 руб.",
      "status": null,
      "main_activity": "47.11 торговля розничная преимущественно пищевыми продуктами, включая напитки, и табачными изделиями в неспециализированных магазинах",
      "main_activity_code": 471100,
      "address": "454085, челябинская область, город челябинск, моховая улица, дом 7 корпус 1, офис 202"
   },
   {
      "title": "ооо \"вестбалт\"",
      "link": "/id/11764163",
      "head_title": "генеральный директор",
      "head_name": "кириллова наталья владимировна",
      "inn": "7804643533",
      "ogrn": "1197847091771",
      "reg_date": "15 апреля 2019 г.",
      "reg_cap": "20 000 руб.",
      "status": null,
      "main_activity": "47.11 торговля розничная преимущественно пищевыми продуктами, включая напитки, и табачными изделиями в неспециализированных магазинах",
      "main_activity_code": 471100,
      "address": "195009, город санкт-петербург, улица ватутина, дом 8/7 литер а, пом. 6 н офис 4 а"
   },
   {
      "title": "ооо \"джи эс\"",
      "link": "/id/11766715",
      "head_title": "директор",
      "head_name": "гайденко сергей павлович",
      "inn": "6163214433",
      "ogrn": "1196196017335",
      "reg_date": "17 апреля 2019 г.",
      "reg_cap": "10 000 руб.",
      "status": null,
      "main_activity": "47.11 торговля розничная преимущественно пищевыми продуктами, включая напитки, и табачными изделиями в неспециализированных магазинах",
      "main_activity_code": 471100,
      "address": "344006, ростовская область, город ростов-на-дону, улица суворова, дом 55, комната 35"
   },
   {
      "title": "ооо \"огонек\"",
      "link": "/id/11766924",
      "head_title": "директор",
      "head_name": "матющенко анна константиновна",
      "inn": "5404088271",
      "ogrn": "1195476030529",
      "reg_date": "17 апреля 2019 г.",
      "reg_cap": "10 000 руб.",
      "status": null,
      "main_activity": "47.11 торговля розничная преимущественно пищевыми продуктами, включая напитки, и табачными изделиями в неспециализированных магазинах",
      "main_activity_code": 471100,
      "address": "630073, новосибирская область, город новосибирск, проспект карла маркса, дом 57, этаж/пом 1/160"
   },
   {
      "title": "ооо \"анрика\"",
      "link": "/id/11767995",
      "head_title": "директор",
      "head_name": "ефремова ирина алексеевна",
      "inn": "9109023059",
      "ogrn": "1199112007434",
      "reg_date": "18 апреля 2019 г.",
      "reg_cap": "100 000 руб.",
      "status": null,
      "main_activity": "47.11 торговля розничная преимущественно пищевыми продуктами, включая напитки, и табачными изделиями в неспециализированных магазинах",
      "main_activity_code": 471100,
      "address": "297551, республика крым, симферопольский район, село кольчугино, улица революции, дом 39а"
   },
   {
      "title": "ооо \"старт\"",
      "link": "/id/11768158",
      "head_title": "генеральный директор",
      "head_name": "магеррамов тофиг нариман оглы",
      "inn": "7805749564",
      "ogrn": "1197847095412",
      "reg_date": "18 апреля 2019 г.",
      "reg_cap": "10 000 руб.",
      "status": null,
      "main_activity": "47.11 торговля розничная преимущественно пищевыми продуктами, включая напитки, и табачными изделиями в неспециализированных магазинах",
      "main_activity_code": 471100,
      "address": "198035, город санкт-петербург, двинская улица, дом 10 литер а, квартира 4"
   },
   {
      "title": "ооо \"тд \"империя\"",
      "link": "/id/11768206",
      "head_title": "директор",
      "head_name": "кагункин иван анатольевич",
      "inn": "7719491103",
      "ogrn": "1197746274219",
      "reg_date": "19 апреля 2019 г.",
      "reg_cap": "250 000 руб.",
      "status": null,
      "main_activity": "47.11 торговля розничная преимущественно пищевыми продуктами, включая напитки, и табачными изделиями в неспециализированных магазинах",
      "main_activity_code": 471100,
      "address": "105203, город москва, парковая 14-я улица, дом 8, этаж 5 пом i ком 1 оф 26"
   },
   {
      "title": "ооо \"градус\"",
      "link": "/id/11769127",
      "head_title": "генеральный директор",
      "head_name": "биленко алексей игоревич",
      "inn": "2706033185",
      "ogrn": "1192724008916",
      "reg_date": "19 апреля 2019 г.",
      "reg_cap": "50 000 руб.",
      "status": null,
      "main_activity": "47.11 торговля розничная преимущественно пищевыми продуктами, включая напитки, и табачными изделиями в неспециализированных магазинах",
      "main_activity_code": 471100,
      "address": "682640, хабаровский край, город амурск, проспект строителей, дом 6"
   },
   {
      "title": "ооо\"градус\"",
      "link": "/id/11769543",
      "head_title": "генеральный директор",
      "head_name": "евгеньева наталья алексеевна",
      "inn": "7807227429",
      "ogrn": "1197847097172",
      "reg_date": "19 апреля 2019 г.",
      "reg_cap": "1 000 000 руб.",
      "status": null,
      "main_activity": "47.11 торговля розничная преимущественно пищевыми продуктами, включая напитки, и табачными изделиями в неспециализированных магазинах",
      "main_activity_code": 471100,
      "address": "198320, город санкт-петербург, город красное село, проспект ленина, дом 63 корпус 1 литер а, часть помещения 1-н (часть комнаты 28)"
   },
   {
      "title": "ооо \"максимум\"",
      "link": "/id/11769676",
      "head_title": "генеральный директор",
      "head_name": "шаблинский максим валерьевич",
      "inn": "7720462347",
      "ogrn": "1197746275715",
      "reg_date": "19 апреля 2019 г.",
      "reg_cap": "10 000 руб.",
      "status": null,
      "main_activity": "47.11 торговля розничная преимущественно пищевыми продуктами, включая напитки, и табачными изделиями в неспециализированных магазинах",
      "main_activity_code": 471100,
      "address": "111394, город москва, перовская улица, дом 66 корпус 9, эт 1 пом 12 оф 11"
   },
   {
      "title": "ооо \"опт-запад\"",
      "link": "/id/11769717",
      "head_title": "генеральный директор",
      "head_name": "закиров константин иванович",
      "inn": "9723084312",
      "ogrn": "1197746275308",
      "reg_date": "19 апреля 2019 г.",
      "reg_cap": "300 000 руб.",
      "status": null,
      "main_activity": "47.11 торговля розничная преимущественно пищевыми продуктами, включая напитки, и табачными изделиями в неспециализированных магазинах",
      "main_activity_code": 471100,
      "address": "109559, город москва, улица марьинский парк, дом 45, эт 1 пом xvii оф 8"
   },
   {
      "title": "ооо \"евразия тобакко\"",
      "link": "/id/11769858",
      "head_title": "генеральный директор",
      "head_name": "агаларов заур зербалиевич",
      "inn": "7713467030",
      "ogrn": "1197746273856",
      "reg_date": "19 апреля 2019 г.",
      "reg_cap": "10 000 руб.",
      "status": null,
      "main_activity": "47.11 торговля розничная преимущественно пищевыми продуктами, включая напитки, и табачными изделиями в неспециализированных магазинах",
      "main_activity_code": 471100,
      "address": "127434, город москва, дмитровское шоссе, дом 33 корпус 1, эт 1 пом xiii ком 4"
   },
   {
      "title": "ооо \"главметропродукт\"",
      "link": "/id/11769896",
      "head_title": "генеральный директор",
      "head_name": "дунина ирина евгеньевна",
      "inn": "7751161332",
      "ogrn": "1197746273317",
      "reg_date": "19 апреля 2019 г.",
      "reg_cap": "10 000 руб.",
      "status": null,
      "main_activity": "47.11 торговля розничная преимущественно пищевыми продуктами, включая напитки, и табачными изделиями в неспециализированных магазинах",
      "main_activity_code": 471100,
      "address": "108828, город москва, поселение краснопахорское, деревня красная пахра, северный проезд, дом 1"
   },
   {
      "title": "ооо \"лесторг\"",
      "link": "/id/3964050",
      "head_title": "генеральный директор",
      "head_name": "баринова ирина анатольевна",
      "inn": "1102025398",
      "ogrn": "1021100733367",
      "reg_date": "27 октября 1999 г.",
      "reg_cap": "10 000 руб.",
      "status": null,
      "main_activity": "47.11 торговля розничная преимущественно пищевыми продуктами, включая напитки, и табачными изделиями в неспециализированных магазинах",
      "main_activity_code": 471100,
      "address": "169360, республика коми, город ухта, поселок городского типа боровой, лесная улица, 12"
   },
   {
      "title": "ооо \"андол\"",
      "link": "/id/348642",
      "head_title": "генеральный директор",
      "head_name": "аргунова виктория геннадьевна",
      "inn": "2508013959",
      "ogrn": "1022500698857",
      "reg_date": "11 октября 1993 г.",
      "reg_cap": "10 000 руб.",
      "status": null,
      "main_activity": "47.11 торговля розничная преимущественно пищевыми продуктами, включая напитки, и табачными изделиями в неспециализированных магазинах",
      "main_activity_code": 471100,
      "address": "692922, приморский край, город находка, улица мичурина, 6а"
   },
   {
      "title": "ооо \"альянс\"",
      "link": "/id/1291661",
      "head_title": "директор",
      "head_name": "андрущенко андрей михайлович",
      "inn": "2616005730",
      "ogrn": "1022602422809",
      "reg_date": "16 ноября 1997 г.",
      "reg_cap": "10 000 руб.",
      "status": null,
      "main_activity": "47.11 торговля розничная преимущественно пищевыми продуктами, включая напитки, и табачными изделиями в неспециализированных магазинах",
      "main_activity_code": 471100,
      "address": "356356, ставропольский край, новоселицкий район, село китаевское, улица гагарина, 44"
   },
   {
      "title": "ооо \"центрагроснаб\"",
      "link": "/id/4283343",
      "head_title": "генеральный директор",
      "head_name": "гулиенко евгений валерьевич",
      "inn": "3123072650",
      "ogrn": "1023101683461",
      "reg_date": "21 августа 2001 г.",
      "reg_cap": null,
      "status": null,
      "main_activity": "47.11 торговля розничная преимущественно пищевыми продуктами, включая напитки, и табачными изделиями в неспециализированных магазинах",
      "main_activity_code": 471100,
      "address": "308009, белгородская область, город белгород, сумская улица, дом 22 этаж 2, офис 1"
   },
   {
      "title": "ооо \"ковбаска и к\"",
      "link": "/id/2148789",
      "head_title": "директор",
      "head_name": "ковбаска валентина петровна",
      "inn": "3922006117",
      "ogrn": "1023902273757",
      "reg_date": "6 февраля 2002 г.",
      "reg_cap": "100 063 руб.",
      "status": "организация в процессе ликвидации",
      "main_activity": "47.11 торговля розничная преимущественно пищевыми продуктами, включая напитки, и табачными изделиями в неспециализированных магазинах",
      "main_activity_code": 471100,
      "address": "238633, калининградская область, полесский район, поселок заливино, колхозная улица, 12"
   },
   {
      "title": "ооо \"магазин no 13\"",
      "link": "/id/714193",
      "head_title": "директор",
      "head_name": "строилова наталья ивановна",
      "inn": "4219000263",
      "ogrn": "1024201822919",
      "reg_date": "30 апреля 1992 г.",
      "reg_cap": "250 000 руб.",
      "status": null,
      "main_activity": "47.11 торговля розничная преимущественно пищевыми продуктами, включая напитки, и табачными изделиями в неспециализированных магазинах",
      "main_activity_code": 471100,
      "address": "654086, кемеровская область, город новокузнецк, улица пржевальского (орджоникидзевский р-н), дом 26, помещение 57"
   },
   {
      "title": "ооо \"свс-2000\"",
      "link": "/id/1384964",
      "head_title": "директор",
      "head_name": "ворсуляк сергей викторович",
      "inn": "5034014145",
      "ogrn": "1025004581910",
      "reg_date": "14 июня 1995 г.",
      "reg_cap": "1 080 000 руб.",
      "status": null,
      "main_activity": "47.11 торговля розничная преимущественно пищевыми продуктами, включая напитки, и табачными изделиями в неспециализированных магазинах",
      "main_activity_code": 471100,
      "address": "142602, московская область, город орехово-зуево, улица серова, дом 18"
   },
   {
      "title": "ооо \"сокольский терминал\"",
      "link": "/id/2536361",
      "head_title": "ликвидатор",
      "head_name": "осина елена анатольевна",
      "inn": "5240003011",
      "ogrn": "1025201681658",
      "reg_date": "12 сентября 2000 г.",
      "reg_cap": "114 000 руб.",
      "status": "организация в процессе ликвидации",
      "main_activity": "47.11 торговля розничная преимущественно пищевыми продуктами, включая напитки, и табачными изделиями в неспециализированных магазинах",
      "main_activity_code": 471100,
      "address": "606670, нижегородская область, сокольский район, рабочий поселок сокольское, ленинградская улица, 78 нет, нет"
   },
   {
      "title": "ооо \"панорама\"",
      "link": "/id/2407763",
      "head_title": "ликвидатор",
      "head_name": "астанин дмитрий николаевич",
      "inn": "7205010605",
      "ogrn": "1027201235896",
      "reg_date": "26 сентября 2001 г.",
      "reg_cap": "300 000 руб.",
      "status": "организация в процессе ликвидации",
      "main_activity": "47.11 торговля розничная преимущественно пищевыми продуктами, включая напитки, и табачными изделиями в неспециализированных магазинах",
      "main_activity_code": 471100,
      "address": "627705, тюменская область, город ишим, улица калинина, 108"
   },
   {
      "title": "ооо \"ато\"",
      "link": "/id/287203",
      "head_title": "директор",
      "head_name": "сухачев андрей евгеньевич",
      "inn": "7604055397",
      "ogrn": "1027600681790",
      "reg_date": "15 октября 2001 г.",
      "reg_cap": "150 000 000 руб.",
      "status": null,
      "main_activity": "47.11 торговля розничная преимущественно пищевыми продуктами, включая напитки, и табачными изделиями в неспециализированных магазинах",
      "main_activity_code": 471100,
      "address": "152903, ярославская область, рыбинский район, город рыбинск, проспект ленина, 163"
   },
   {
      "title": "ооо \"инат\"",
      "link": "/id/3191004",
      "head_title": "директор",
      "head_name": "поскальнюк алексей игоревич",
      "inn": "7103033610",
      "ogrn": "1037100126447",
      "reg_date": "18 ноября 2003 г.",
      "reg_cap": "501 000 руб.",
      "status": null,
      "main_activity": "47.11 торговля розничная преимущественно пищевыми продуктами, включая напитки, и табачными изделиями в неспециализированных магазинах",
      "main_activity_code": 471100,
      "address": "300062, тульская область, город тула, октябрьская улица, дом 95 корпус в"
   },
   {
      "title": "ооо \"евро xxi\"",
      "link": "/id/4129433",
      "head_title": "генеральный директор",
      "head_name": "хирамагомедов хирамагомед ибрагимхалилович",
      "inn": "7728259072",
      "ogrn": "1037739427252",
      "reg_date": "23 апреля 2002 г.",
      "reg_cap": "1 000 000 руб.",
      "status": null,
      "main_activity": "47.11 торговля розничная преимущественно пищевыми продуктами, включая напитки, и табачными изделиями в неспециализированных магазинах",
      "main_activity_code": 471100,
      "address": "117133, город москва, улица академика варги, 40, 173"
   },
   {
      "title": "ооо \"фирма \"элида\"",
      "link": "/id/3989804",
      "head_title": "генеральный директор",
      "head_name": "карабеков илхом облаевич",
      "inn": "7726195850",
      "ogrn": "1037739772828",
      "reg_date": "21 февраля 2002 г.",
      "reg_cap": "10 000 руб.",
      "status": null,
      "main_activity": "47.11 торговля розничная преимущественно пищевыми продуктами, включая напитки, и табачными изделиями в неспециализированных магазинах",
      "main_activity_code": 471100,
      "address": "117218, город москва, улица черёмушкинская б., 3 стр.1"
   },
   {
      "title": "ооо \"росы\"",
      "link": "/id/4308518",
      "head_title": "директор",
      "head_name": "матюнин александр дмитриевич",
      "inn": "4238017897",
      "ogrn": "1054238048523",
      "reg_date": "5 декабря 2005 г.",
      "reg_cap": "300 000 руб.",
      "status": null,
      "main_activity": "47.11 торговля розничная преимущественно пищевыми продуктами, включая напитки, и табачными изделиями в неспециализированных магазинах",
      "main_activity_code": 471100,
      "address": "654202, кемеровская область, новокузнецкий район, село куртуково, улица зорькина, дом 2, помещение 1"
   },
   {
      "title": "ооо \"каскад\"",
      "link": "/id/639658",
      "head_title": "генеральный директор",
      "head_name": "смоилова кристина петровна",
      "inn": "0917002640",
      "ogrn": "1060917004510",
      "reg_date": "2 марта 2006 г.",
      "reg_cap": "50 000 руб.",
      "status": null,
      "main_activity": "47.11 торговля розничная преимущественно пищевыми продуктами, включая напитки, и табачными изделиями в неспециализированных магазинах",
      "main_activity_code": 471100,
      "address": "369114, республика карачаево-черкесская, прикубанский район, поселок городского типа ударный, площадь мира, 4"
   },
   {
      "title": "ооо \"встреча\"",
      "link": "/id/4311668",
      "head_title": "директор",
      "head_name": "пашков михаил геннадьевич",
      "inn": "1835069290",
      "ogrn": "1061841020120",
      "reg_date": "3 марта 2006 г.",
      "reg_cap": "200 000 руб.",
      "status": null,
      "main_activity": "47.11 торговля розничная преимущественно пищевыми продуктами, включая напитки, и табачными изделиями в неспециализированных магазинах",
      "main_activity_code": 471100,
      "address": "426053, республика удмуртская, город ижевск, салютовская улица, дом 15, офис 11"
   },
   {
      "title": "ооо \"нара\"",
      "link": "/id/3516067",
      "head_title": "директор",
      "head_name": "паповян карапет сергеевич",
      "inn": "2317042483",
      "ogrn": "1062317000932",
      "reg_date": "13 февраля 2006 г.",
      "reg_cap": "10 000 руб.",
      "status": null,
      "main_activity": "47.11 торговля розничная преимущественно пищевыми продуктами, включая напитки, и табачными изделиями в неспециализированных магазинах",
      "main_activity_code": 471100,
      "address": "354364, краснодарский край, город сочи, улица чкалова, 38 а"
   },
   {
      "title": "ооо \"платинум\"",
      "link": "/id/3279855",
      "head_title": "директор",
      "head_name": "игнатова ирина ислановна",
      "inn": "2318033202",
      "ogrn": "1062318007454",
      "reg_date": "18 декабря 2006 г.",
      "reg_cap": "10 000 руб.",
      "status": null,
      "main_activity": "47.11 торговля розничная преимущественно пищевыми продуктами, включая напитки, и табачными изделиями в неспециализированных магазинах",
      "main_activity_code": 471100,
      "address": "354200, краснодарский край, город сочи, улица калараша, 165"
   },
   {
      "title": "ооо \"виктория - о\"",
      "link": "/id/3726408",
      "head_title": "директор",
      "head_name": "найдишкина ольга владимировна",
      "inn": "2452031576",
      "ogrn": "1062452003052",
      "reg_date": "20 февраля 2006 г.",
      "reg_cap": "130 000 руб.",
      "status": null,
      "main_activity": "47.11 торговля розничная преимущественно пищевыми продуктами, включая напитки, и табачными изделиями в неспециализированных магазинах",
      "main_activity_code": 471100,
      "address": "662971, красноярский край, город железногорск, улица ленина, 24, 43"
   },
   {
      "title": "ооо \"славяне\"",
      "link": "/id/3101562",
      "head_title": "генеральный директор",
      "head_name": "ласуков виктор александрович",
      "inn": "3608004212",
      "ogrn": "1063610004226",
      "reg_date": "20 марта 2006 г.",
      "reg_cap": "300 000 руб.",
      "status": null,
      "main_activity": "47.11 торговля розничная преимущественно пищевыми продуктами, включая напитки, и табачными изделиями в неспециализированных магазинах",
      "main_activity_code": 471100,
      "address": "397570, воронежская область, воробьевский район, село воробьевка, улица гоголя, 14"
   },
   {
      "title": "ооо \"рпс\"",
      "link": "/id/525730",
      "head_title": "директор",
      "head_name": "моисеева юлия сергеевна",
      "inn": "6317064678",
      "ogrn": "1066317028601",
      "reg_date": "22 июня 2006 г.",
      "reg_cap": "10 000 руб.",
      "status": null,
      "main_activity": "47.11 торговля розничная преимущественно пищевыми продуктами, включая напитки, и табачными изделиями в неспециализированных магазинах",
      "main_activity_code": 471100,
      "address": "443099, самарская область, город самара, галактионовская улица, 62, 4"
   },
   {
      "title": "ооо \"балтика\"",
      "link": "/id/2337993",
      "head_title": "директор",
      "head_name": "броян гаянэ алваровна",
      "inn": "7203181274",
      "ogrn": "1067203345395",
      "reg_date": "4 сентября 2006 г.",
      "reg_cap": "516 190 руб.",
      "status": null,
      "main_activity": "47.11 торговля розничная преимущественно пищевыми продуктами, включая напитки, и табачными изделиями в неспециализированных магазинах",
      "main_activity_code": 471100,
      "address": "625046, тюменская область, город тюмень, широтная улица, 114-в"
   },
   {
      "title": "ооо \"юринфо\"",
      "link": "/id/3564920",
      "head_title": "управляющий - индивидуальный предприниматель",
      "head_name": "лисуненко геннадий федорович",
      "inn": "1901083639",
      "ogrn": "1081901001192",
      "reg_date": "25 марта 2008 г.",
      "reg_cap": "10 000 руб.",
      "status": null,
      "main_activity": "47.11 торговля розничная преимущественно пищевыми продуктами, включая напитки, и табачными изделиями в неспециализированных магазинах",
      "main_activity_code": 471100,
      "address": "655009, республика хакасия, город абакан, улица стофато, 4, 76"
   },
   {
      "title": "ооо \"рай и к\"",
      "link": "/id/2926739",
      "head_title": "генеральный директор",
      "head_name": "глухова елена евгеньевна",
      "inn": "4214029614",
      "ogrn": "1084214001145",
      "reg_date": "27 августа 2008 г.",
      "reg_cap": "250 000 руб.",
      "status": null,
      "main_activity": "47.11 торговля розничная преимущественно пищевыми продуктами, включая напитки, и табачными изделиями в неспециализированных магазинах",
      "main_activity_code": 471100,
      "address": "654218, кемеровская область, новокузнецкий район, село безруково, коммунальная улица, дом 1"
   },
   {
      "title": "по \"киснемское\"",
      "link": "/id/457095",
      "head_title": "председатель правления",
      "head_name": "коничева галина викторовна",
      "inn": "3504026518",
      "ogrn": "1093533000131",
      "reg_date": "13 марта 2009 г.",
      "reg_cap": null,
      "status": null,
      "main_activity": "47.11 торговля розничная преимущественно пищевыми продуктами, включая напитки, и табачными изделиями в неспециализированных магазинах",
      "main_activity_code": 471100,
      "address": "161250, вологодская область, вашкинский район, село липин бор, октябрьская улица, 1а"
   },
   {
      "title": "по \"вашкинское\"",
      "link": "/id/869021",
      "head_title": "председатель правления",
      "head_name": "машина елена юрьевна",
      "inn": "3504026525",
      "ogrn": "1093533000142",
      "reg_date": "13 марта 2009 г.",
      "reg_cap": null,
      "status": null,
      "main_activity": "47.11 торговля розничная преимущественно пищевыми продуктами, включая напитки, и табачными изделиями в неспециализированных магазинах",
      "main_activity_code": 471100,
      "address": "161250, вологодская область, вашкинский район, село липин бор, октябрьская улица, 1а"
   },
   {
      "title": "ооо \"абшерон\"",
      "link": "/id/5436489",
      "head_title": "директор",
      "head_name": "гусейнов фариз фазил-оглы",
      "inn": "1838008458",
      "ogrn": "1101838001231",
      "reg_date": "21 октября 2010 г.",
      "reg_cap": "204 000 руб.",
      "status": null,
      "main_activity": "47.11 торговля розничная преимущественно пищевыми продуктами, включая напитки, и табачными изделиями в неспециализированных магазинах",
      "main_activity_code": 471100,
      "address": "427960, республика удмуртская, город сарапул, улица карла маркса, 19, 1"
   },
   {
      "title": "ооо \"скорпион \"",
      "link": "/id/5641875",
      "head_title": "генеральный директор",
      "head_name": "москаева анна михайловна",
      "inn": "1003005256",
      "ogrn": "1111039000380",
      "reg_date": "22 июня 2011 г.",
      "reg_cap": "400 000 руб.",
      "status": null,
      "main_activity": "47.11 торговля розничная преимущественно пищевыми продуктами, включая напитки, и табачными изделиями в неспециализированных магазинах",
      "main_activity_code": 471100,
      "address": "186215, республика карелия, кондопожский район, деревня юркостров, школьная улица, 1, 1"
   },
   {
      "title": "ооо \"ритм\"",
      "link": "/id/5723514",
      "head_title": "директор",
      "head_name": "пуговкин александр евгеньевич",
      "inn": "7111503796",
      "ogrn": "1117154020411",
      "reg_date": "18 июля 2011 г.",
      "reg_cap": "500 000 руб.",
      "status": null,
      "main_activity": "47.11 торговля розничная преимущественно пищевыми продуктами, включая напитки, и табачными изделиями в неспециализированных магазинах",
      "main_activity_code": 471100,
      "address": "301369, тульская область, алексинский район, город алексин, улица революции, 7, 49"
   },
   {
      "title": "ооо \"авк групп\"",
      "link": "/id/6970566",
      "head_title": "генеральный директор",
      "head_name": "козьмина анна вячеславовна",
      "inn": "2540193801",
      "ogrn": "1132540007380",
      "reg_date": "30 июля 2013 г.",
      "reg_cap": "10 000 руб.",
      "status": null,
      "main_activity": "47.11 торговля розничная преимущественно пищевыми продуктами, включая напитки, и табачными изделиями в неспециализированных магазинах",
      "main_activity_code": 471100,
      "address": "690105, приморский край, город владивосток, русская улица, дом 94а, помещение 3"
   },
   {
      "title": "ооо \"василек\"",
      "link": "/id/6683889",
      "head_title": "генеральный директор",
      "head_name": "учайкина вера ивановна",
      "inn": "5812902058",
      "ogrn": "1135826000078",
      "reg_date": "24 января 2013 г.",
      "reg_cap": "10 000 руб.",
      "status": null,
      "main_activity": "47.11 торговля розничная преимущественно пищевыми продуктами, включая напитки, и табачными изделиями в неспециализированных магазинах",
      "main_activity_code": 471100,
      "address": "442341, пензенская область, городищенский район, село дигилевка, центральная улица, 1"
   },
   {
      "title": "ооо \"мегаимпорт\"",
      "link": "/id/7059039",
      "head_title": "генеральный директор",
      "head_name": "мещеряков денис игоревич",
      "inn": "6829096859",
      "ogrn": "1136829009019",
      "reg_date": "20 декабря 2013 г.",
      "reg_cap": "51 000 руб.",
      "status": "организация в процессе реорганизации",
      "main_activity": "47.11 торговля розничная преимущественно пищевыми продуктами, включая напитки, и табачными изделиями в неспециализированных магазинах",
      "main_activity_code": 471100,
      "address": "392003, тамбовская область, город тамбов, бульвар энтузиастов, 2 а"
   },
   {
      "title": "ооо \"меркурий\"",
      "link": "/id/7102225",
      "head_title": "генеральный директор",
      "head_name": "ибрагимов сахиб мамед оглы",
      "inn": "7723885742",
      "ogrn": "1137746926514",
      "reg_date": "9 октября 2013 г.",
      "reg_cap": "1 000 000 руб.",
      "status": null,
      "main_activity": "47.11 торговля розничная преимущественно пищевыми продуктами, включая напитки, и табачными изделиями в неспециализированных магазинах",
      "main_activity_code": 471100,
      "address": "109382, город москва, улица верхние поля, дом 35 корпус 4"
   },
   {
      "title": "ооо \"радуга\"",
      "link": "/id/7034174",
      "head_title": "генеральный директор",
      "head_name": "джафаров вугар магамед оглы",
      "inn": "7802843664",
      "ogrn": "1137847451631",
      "reg_date": "22 ноября 2013 г.",
      "reg_cap": "20 000 руб.",
      "status": null,
      "main_activity": "47.11 торговля розничная преимущественно пищевыми продуктами, включая напитки, и табачными изделиями в неспециализированных магазинах",
      "main_activity_code": 471100,
      "address": "194100, город санкт-петербург, кантемировская улица, дом 39 литер а"
   },
   {
      "title": "ооо \"тдст\"",
      "link": "/id/7181313",
      "head_title": "генеральный директор",
      "head_name": "трубецкой игорь вениаминович",
      "inn": "3458000791",
      "ogrn": "1143458000047",
      "reg_date": "5 февраля 2014 г.",
      "reg_cap": "50 000 руб.",
      "status": null,
      "main_activity": "47.11 торговля розничная преимущественно пищевыми продуктами, включая напитки, и табачными изделиями в неспециализированных магазинах",
      "main_activity_code": 471100,
      "address": "404174, волгоградская область, светлоярский район, село большие чапурники, улица ильина, 37 в"
   },
   {
      "title": "ооо \"м-3\"",
      "link": "/id/7568717",
      "head_title": "директор",
      "head_name": "охотникова наталия рудольфовна",
      "inn": "3525330999",
      "ogrn": "1143525015611",
      "reg_date": "15 августа 2014 г.",
      "reg_cap": "500 000 руб.",
      "status": null,
      "main_activity": "47.11 торговля розничная преимущественно пищевыми продуктами, включая напитки, и табачными изделиями в неспециализированных магазинах",
      "main_activity_code": 471100,
      "address": "160000, вологодская область, город вологда, козленская улица, дом 42, офис 806"
   },
   {
      "title": "ооо \"сервис плюс\"",
      "link": "/id/7804743",
      "head_title": "директор",
      "head_name": "клочков михаил михайлович",
      "inn": "6234139418",
      "ogrn": "1146234024463",
      "reg_date": "29 декабря 2014 г.",
      "reg_cap": "400 000 руб.",
      "status": null,
      "main_activity": "47.11 торговля розничная преимущественно пищевыми продуктами, включая напитки, и табачными изделиями в неспециализированных магазинах",
      "main_activity_code": 471100,
      "address": "390013, рязанская область, город рязань, московское шоссе, дом 5а литера а, помещение 4.2"
   },
   {
      "title": "ооо \"антан\"",
      "link": "/id/7525757",
      "head_title": "директор",
      "head_name": "антоненко сергей михайлович",
      "inn": "9111004141",
      "ogrn": "1149102079026",
      "reg_date": "11 ноября 2014 г.",
      "reg_cap": "100 000 руб.",
      "status": null,
      "main_activity": "47.11 торговля розничная преимущественно пищевыми продуктами, включая напитки, и табачными изделиями в неспециализированных магазинах",
      "main_activity_code": 471100,
      "address": "298200, республика крым, ленинский район, поселок городского типа ленино, улица энгельса, дом 12"
   },
   {
      "title": "ооо \"пкф \"антант\"",
      "link": "/id/7334896",
      "head_title": "генеральный директор",
      "head_name": "тимакова надежда михайловна",
      "inn": "9201008140",
      "ogrn": "1149204024111",
      "reg_date": "4 сентября 1992 г.",
      "reg_cap": "10 000 руб.",
      "status": null,
      "main_activity": "47.11 торговля розничная преимущественно пищевыми продуктами, включая напитки, и табачными изделиями в неспециализированных магазинах",
      "main_activity_code": 471100,
      "address": "299057, город севастополь, улица адмирала юмашева, дом 26-б"
   },
   {
      "title": "ооо \"са.ва\"",
      "link": "/id/7441360",
      "head_title": "директор",
      "head_name": "пынзару наталья михайловна",
      "inn": "9204012963",
      "ogrn": "1149204026443",
      "reg_date": "22 октября 2014 г.",
      "reg_cap": "100 000 руб.",
      "status": null,
      "main_activity": "47.11 торговля розничная преимущественно пищевыми продуктами, включая напитки, и табачными изделиями в неспециализированных магазинах",
      "main_activity_code": 471100,
      "address": "299007, город севастополь, музыки николая улица, дом 42, квартира 60"
   },
   {
      "title": "ооо \"крестовый туз\"",
      "link": "/id/7331725",
      "head_title": "директор",
      "head_name": "годияк мария владимировна",
      "inn": "9201009296",
      "ogrn": "1149204027455",
      "reg_date": "12 июня 1997 г.",
      "reg_cap": "697 137,18 руб.",
      "status": null,
      "main_activity": "47.11 торговля розничная преимущественно пищевыми продуктами, включая напитки, и табачными изделиями в неспециализированных магазинах",
      "main_activity_code": 471100,
      "address": "299038, город севастополь, улица колобова, дом 21, встроенные нежилые помещения с no i по no viii"
   },
   {
      "title": "ооо \"рыбфлот\"",
      "link": "/id/7333880",
      "head_title": "директор",
      "head_name": "бублик андрей олегович",
      "inn": "9201010855",
      "ogrn": "1149204032867",
      "reg_date": "9 ноября 1993 г.",
      "reg_cap": "3 532 392 руб.",
      "status": null,
      "main_activity": "47.11 торговля розничная преимущественно пищевыми продуктами, включая напитки, и табачными изделиями в неспециализированных магазинах",
      "main_activity_code": 471100,
      "address": "299058, город севастополь, пролетарская улица, дом 33-а"
   },
   {
      "title": "ооо \"виалан\"",
      "link": "/id/7530387",
      "head_title": "генеральный директор",
      "head_name": "харлова виктория ильинична",
      "inn": "9201010894",
      "ogrn": "1149204032977",
      "reg_date": "10 ноября 2014 г.",
      "reg_cap": "100 000 руб.",
      "status": null,
      "main_activity": "47.11 торговля розничная преимущественно пищевыми продуктами, включая напитки, и табачными изделиями в неспециализированных магазинах",
      "main_activity_code": 471100,
      "address": "299057, город севастополь, проспект октябрьской революции, дом 25"
   },
   {
      "title": "ооо \"виктория\"",
      "link": "/id/7530550",
      "head_title": "директор",
      "head_name": "сорокина людмила ивановна",
      "inn": "9201012267",
      "ogrn": "1149204037355",
      "reg_date": "21 ноября 2014 г.",
      "reg_cap": "100 000 руб.",
      "status": null,
      "main_activity": "47.11 торговля розничная преимущественно пищевыми продуктами, включая напитки, и табачными изделиями в неспециализированных магазинах",
      "main_activity_code": 471100,
      "address": "299038, город севастополь, проспект октябрьской революции, дом 26, квартира 352 а"
   },
   {
      "title": "ооо \"холдинг - \"наш\"",
      "link": "/id/7730179",
      "head_title": "директор",
      "head_name": "григорян арташес лаврентьевич",
      "inn": "2318041700",
      "ogrn": "1152366006100",
      "reg_date": "21 июля 2015 г.",
      "reg_cap": "10 000 руб.",
      "status": null,
      "main_activity": "47.11 торговля розничная преимущественно пищевыми продуктами, включая напитки, и табачными изделиями в неспециализированных магазинах",
      "main_activity_code": 471100,
      "address": "354207, краснодарский край, город сочи, армавирская улица, дом 73"
   },
   {
      "title": "ооо \"капитал плюс\"",
      "link": "/id/7897134",
      "head_title": "генеральный директор",
      "head_name": "баданова субадма ширапнимаевна",
      "inn": "3811046315",
      "ogrn": "1153850045645",
      "reg_date": "29 октября 2015 г.",
      "reg_cap": "60 000 руб.",
      "status": null,
      "main_activity": "47.11 торговля розничная преимущественно пищевыми продуктами, включая напитки, и табачными изделиями в неспециализированных магазинах",
      "main_activity_code": 471100,
      "address": "664023, иркутская область, город иркутск, улица ядринцева, дом 92"
   },
   {
      "title": "ооо \"океан\"",
      "link": "/id/10199191",
      "head_title": "директор",
      "head_name": "симонян юлия петровна",
      "inn": "7457006195",
      "ogrn": "1157456020105",
      "reg_date": "30 октября 2015 г.",
      "reg_cap": "100 000 руб.",
      "status": null,
      "main_activity": "47.11 торговля розничная преимущественно пищевыми продуктами, включая напитки, и табачными изделиями в неспециализированных магазинах",
      "main_activity_code": 471100,
      "address": "456080, челябинская область, город трехгорный, улица островского, дом 29, квартира 9"
   },
   {
      "title": "ооо \"а-системы\"",
      "link": "/id/7621611",
      "head_title": "генеральный директор",
      "head_name": "батуров роман олегович",
      "inn": "7840028607",
      "ogrn": "1157847111290",
      "reg_date": "31 марта 2015 г.",
      "reg_cap": "40 000 руб.",
      "status": null,
      "main_activity": "47.11 торговля розничная преимущественно пищевыми продуктами, включая напитки, и табачными изделиями в неспециализированных магазинах",
      "main_activity_code": 471100,
      "address": "191025, город санкт-петербург, колокольная улица, дом 5 литер а, помещение 6-н"
   },
   {
      "title": "ооо \"эмиль\"",
      "link": "/id/7599826",
      "head_title": "ликвидатор",
      "head_name": "гемидже эмиль бекирович",
      "inn": "9107037828",
      "ogrn": "1159102084349",
      "reg_date": "2 апреля 2015 г.",
      "reg_cap": "100 000 руб.",
      "status": "организация в процессе ликвидации",
      "main_activity": "47.11 торговля розничная преимущественно пищевыми продуктами, включая напитки, и табачными изделиями в неспециализированных магазинах",
      "main_activity_code": 471100,
      "address": "296522, республика крым, сакский район, село кольцово, улица к.терещенко, дом 5"
   },
   {
      "title": "ооо \"три-о\"",
      "link": "/id/10655190",
      "head_title": "директор",
      "head_name": "широков сергей николаевич",
      "inn": "1101153982",
      "ogrn": "1161101058249",
      "reg_date": "3 октября 2016 г.",
      "reg_cap": "10 000 руб.",
      "status": null,
      "main_activity": "47.11 торговля розничная преимущественно пищевыми продуктами, включая напитки, и табачными изделиями в неспециализированных магазинах",
      "main_activity_code": 471100,
      "address": "167005, республика коми, город сыктывкар, покровский бульвар, дом 9, квартира 104"
   },
   {
      "title": "ооо \"биллион\"",
      "link": "/id/10333029",
      "head_title": "генеральный директор",
      "head_name": "сапожникова лидия александровна",
      "inn": "2130166410",
      "ogrn": "1162130051214",
      "reg_date": "2 февраля 2016 г.",
      "reg_cap": "10 000 руб.",
      "status": null,
      "main_activity": "47.11 торговля розничная преимущественно пищевыми продуктами, включая напитки, и табачными изделиями в неспециализированных магазинах",
      "main_activity_code": 471100,
      "address": "428001, чувашская республика - чувашия, город чебоксары, проспект максима горького, дом 10, строение 1"
   },
   {
      "title": "ооо \"дарвик\"",
      "link": "/id/10318302",
      "head_title": "генеральный директор",
      "head_name": "шмаков андрей викторович",
      "inn": "7731304462",
      "ogrn": "1167746073208",
      "reg_date": "19 января 2016 г.",
      "reg_cap": "1 000 000 руб.",
      "status": null,
      "main_activity": "47.11 торговля розничная преимущественно пищевыми продуктами, включая напитки, и табачными изделиями в неспециализированных магазинах",
      "main_activity_code": 471100,
      "address": "121351, город москва, кунцевская улица, дом 4 корпус 1, этаж 1 помещение vii к 1"
   }
]