[
   {
      "title": "ооо \"лакшери\"",
      "link": "/id/7522002",
      "head_title": "генеральный директор",
      "head_name": "миронов никита сергеевич",
      "inn": "7820338865",
      "ogrn": "1147847403956",
      "reg_date": "20 ноября 2014 г.",
      "reg_cap": "10 000 руб.",
      "status": null,
      "main_activity": "56.30 подача напитков",
      "main_activity_code": 563000,
      "address": "196608, город санкт-петербург, город пушкин, железнодорожная улица, дом 56а литер н, помещение 9-н"
   },
   {
      "title": "ооо \"империя\"",
      "link": "/id/7861898",
      "head_title": "генеральный директор",
      "head_name": "обенин егор николаевич",
      "inn": "7707335501",
      "ogrn": "1157746203449",
      "reg_date": "18 марта 2015 г.",
      "reg_cap": "25 000 руб.",
      "status": null,
      "main_activity": "56.30 подача напитков",
      "main_activity_code": 563000,
      "address": "127051, город москва, цветной бульвар, дом 11 строение 2"
   },
   {
      "title": "ооо \"альфа-4\"",
      "link": "/id/7885840",
      "head_title": "генеральный директор",
      "head_name": "новосельцев сергей александрович",
      "inn": "7804184590",
      "ogrn": "1157847049656",
      "reg_date": "17 февраля 2015 г.",
      "reg_cap": "20 000 руб.",
      "status": null,
      "main_activity": "56.30 подача напитков",
      "main_activity_code": 563000,
      "address": "195427, город санкт-петербург, светлановский проспект, дом 40 корпус 1 лит. а"
   },
   {
      "title": "ооо \"акакао\"",
      "link": "/id/7634263",
      "head_title": "генеральный директор",
      "head_name": "яковлева юлия борисовна",
      "inn": "7810348110",
      "ogrn": "1157847140164",
      "reg_date": "20 апреля 2015 г.",
      "reg_cap": "10 000 руб.",
      "status": null,
      "main_activity": "56.30 подача напитков",
      "main_activity_code": 563000,
      "address": "196233, город санкт-петербург, проспект космонавтов, дом 92, квартира 55"
   },
   {
      "title": "ооо \"счастье на рубинштейна\"",
      "link": "/id/7631187",
      "head_title": "генеральный директор",
      "head_name": "головина елена сергеевна",
      "inn": "7804208643",
      "ogrn": "1157847141594",
      "reg_date": "20 апреля 2015 г.",
      "reg_cap": "10 000 руб.",
      "status": null,
      "main_activity": "56.30 подача напитков",
      "main_activity_code": 563000,
      "address": "191002, город санкт-петербург, улица рубинштейна, дом 15-17 литера а, помещение 73 н"
   },
   {
      "title": "ооо \"успех\"",
      "link": "/id/7711320",
      "head_title": "генеральный директор",
      "head_name": "ащин иван геннадьевич",
      "inn": "7810350599",
      "ogrn": "1157847158842",
      "reg_date": "5 мая 2015 г.",
      "reg_cap": "10 000 руб.",
      "status": null,
      "main_activity": "56.30 подача напитков",
      "main_activity_code": 563000,
      "address": "196084, город санкт-петербург, московский проспект, дом 109 корпус 3, литер в"
   },
   {
      "title": "ооо \"охрана окружающей среды и животного мира\"",
      "link": "/id/9400036",
      "head_title": "генеральный директор",
      "head_name": "барабадзе шота шалвович",
      "inn": "7806175961",
      "ogrn": "1157847209431",
      "reg_date": "16 июня 2015 г.",
      "reg_cap": "15 500 руб.",
      "status": null,
      "main_activity": "56.30 подача напитков",
      "main_activity_code": 563000,
      "address": "195043, город санкт-петербург, рябовское шоссе, дом 77 литер а, помещение 1н"
   },
   {
      "title": "ооо \"концепт\"",
      "link": "/id/7887410",
      "head_title": "генеральный директор",
      "head_name": "балашов андрей владимирович",
      "inn": "7840037231",
      "ogrn": "1157847263375",
      "reg_date": "31 июля 2015 г.",
      "reg_cap": "10 000 руб.",
      "status": null,
      "main_activity": "56.30 подача напитков",
      "main_activity_code": 563000,
      "address": "197082, город санкт-петербург, туристская улица, дом 30 корпус 1 литер а, квартира 478"
   },
   {
      "title": "ооо \"ленторгко\"",
      "link": "/id/7891859",
      "head_title": "зам.гендиректора",
      "head_name": "луцак константин евгеньевич",
      "inn": "7810382375",
      "ogrn": "1157847321092",
      "reg_date": "21 сентября 2015 г.",
      "reg_cap": "10 000 руб.",
      "status": null,
      "main_activity": "56.30 подача напитков",
      "main_activity_code": 563000,
      "address": "196084, город санкт-петербург, лиговский проспект, дом 256, офис 22"
   },
   {
      "title": "ооо \"бариста клуб\"",
      "link": "/id/10240210",
      "head_title": "инн",
      "head_name": "7806209924",
      "inn": "7806209924",
      "ogrn": "1157847408399",
      "reg_date": "30 ноября 2015 г.",
      "reg_cap": "45 000 руб.",
      "status": null,
      "main_activity": "56.30 подача напитков",
      "main_activity_code": 563000,
      "address": "195027, город санкт-петербург, среднеохтинский проспект, дом 47/9 лит. а, пом. 10-н"
   },
   {
      "title": "ооо \"берли\"",
      "link": "/id/10535356",
      "head_title": "генеральный директор",
      "head_name": "пойсик андрей михайлович",
      "inn": "7702402930",
      "ogrn": "1167746609777",
      "reg_date": "29 июня 2016 г.",
      "reg_cap": "130 000 руб.",
      "status": null,
      "main_activity": "56.30 подача напитков",
      "main_activity_code": 563000,
      "address": "127006, город москва, улица кузнецкий мост, дом 19 строение 1, этаж 1 пом. 1 комн.1-8"
   },
   {
      "title": "ооо \"пи-джи\"",
      "link": "/id/10301556",
      "head_title": "генеральный директор",
      "head_name": "аксенов ален эдуардович",
      "inn": "7814636711",
      "ogrn": "1167847050315",
      "reg_date": "11 января 2016 г.",
      "reg_cap": "12 000 руб.",
      "status": null,
      "main_activity": "56.30 подача напитков",
      "main_activity_code": 563000,
      "address": "197227, город санкт-петербург, проспект испытателей, дом 37 литера а, помещения 72,73,74"
   },
   {
      "title": "ооо \"холостяк спб\"",
      "link": "/id/10311532",
      "head_title": "генеральный директор",
      "head_name": "винокуров артем игоревич",
      "inn": "7814637105",
      "ogrn": "1167847056233",
      "reg_date": "18 января 2016 г.",
      "reg_cap": "25 000 руб.",
      "status": null,
      "main_activity": "56.30 подача напитков",
      "main_activity_code": 563000,
      "address": "197345, город санкт-петербург, мебельная улица, дом 49/92, квартира 201"
   },
   {
      "title": "ооо \"сириус плюс\"",
      "link": "/id/10356667",
      "head_title": "генеральный директор",
      "head_name": "стасюк павел георгиевич",
      "inn": "7819033410",
      "ogrn": "1167847097000",
      "reg_date": "16 февраля 2016 г.",
      "reg_cap": "10 000 руб.",
      "status": null,
      "main_activity": "56.30 подача напитков",
      "main_activity_code": 563000,
      "address": "198412, город санкт-петербург, город ломоносов, александровская улица, дом 45, квартира 56"
   },
   {
      "title": "ооо \"добрый лось\"",
      "link": "/id/10433496",
      "head_title": "генеральный директор",
      "head_name": "лизунов андрей александрович",
      "inn": "7814647840",
      "ogrn": "1167847177618",
      "reg_date": "11 апреля 2016 г.",
      "reg_cap": "10 000 руб.",
      "status": null,
      "main_activity": "56.30 подача напитков",
      "main_activity_code": 563000,
      "address": "197082, город санкт-петербург, мебельная улица, дом 45 корпус 2, квартира 46"
   },
   {
      "title": "ооо \"бронза\"",
      "link": "/id/10434182",
      "head_title": "генеральный директор",
      "head_name": "соболев андрей алексеевич",
      "inn": "7814647907",
      "ogrn": "1167847178729",
      "reg_date": "12 апреля 2016 г.",
      "reg_cap": "10 000 руб.",
      "status": null,
      "main_activity": "56.30 подача напитков",
      "main_activity_code": 563000,
      "address": "197342, город санкт-петербург, ланское шоссе, дом 59 литер а, помещение 3-н"
   },
   {
      "title": "ооо \"чикаго\"",
      "link": "/id/10434727",
      "head_title": "генеральный директор",
      "head_name": "ахмедова маргарита павловна",
      "inn": "7810435700",
      "ogrn": "1167847178971",
      "reg_date": "12 апреля 2016 г.",
      "reg_cap": "10 000 руб.",
      "status": null,
      "main_activity": "56.30 подача напитков",
      "main_activity_code": 563000,
      "address": "196128, город санкт-петербург, варшавская улица, дом 23 корпус 2 литер а, помещение 45н"
   },
   {
      "title": "ооо \"бизнес трейдинг\"",
      "link": "/id/10442392",
      "head_title": "генеральный директор",
      "head_name": "тарасов никита александрович",
      "inn": "7806233444",
      "ogrn": "1167847188530",
      "reg_date": "18 апреля 2016 г.",
      "reg_cap": "1 010 000 руб.",
      "status": null,
      "main_activity": "56.30 подача напитков",
      "main_activity_code": 563000,
      "address": "195299, город санкт-петербург, улица даниила хармса, дом 3 корпус 1 литер а, помещение 11-н"
   },
   {
      "title": "ооо \"фул хаус\"",
      "link": "/id/10456962",
      "head_title": "генеральный директор",
      "head_name": "меркулов александр феликсович",
      "inn": "7810439423",
      "ogrn": "1167847201664",
      "reg_date": "26 апреля 2016 г.",
      "reg_cap": "10 000 руб.",
      "status": null,
      "main_activity": "56.30 подача напитков",
      "main_activity_code": 563000,
      "address": "196070, город санкт-петербург, улица победы, дом 21 литер а, помещение 1н"
   },
   {
      "title": "ооо \"лофт\"",
      "link": "/id/10465525",
      "head_title": "генеральный директор",
      "head_name": "ступакова анна олеговна",
      "inn": "7814650650",
      "ogrn": "1167847210618",
      "reg_date": "5 мая 2016 г.",
      "reg_cap": "10 000 руб.",
      "status": null,
      "main_activity": "56.30 подача напитков",
      "main_activity_code": 563000,
      "address": "197373, город санкт-петербург, проспект авиаконструкторов, дом 32, квартира 206"
   },
   {
      "title": "ооо \"хиггинс\"",
      "link": "/id/10515392",
      "head_title": "генеральный директор",
      "head_name": "лейба владислав владимирович",
      "inn": "7814655009",
      "ogrn": "1167847259315",
      "reg_date": "15 июня 2016 г.",
      "reg_cap": "10 000 руб.",
      "status": null,
      "main_activity": "56.30 подача напитков",
      "main_activity_code": 563000,
      "address": "197372, город санкт-петербург, богатырский проспект, дом 25 корпус 1 лит а, помещение 11-н"
   },
   {
      "title": "ооо \"охта-крафт\"",
      "link": "/id/10633082",
      "head_title": "генеральный директор",
      "head_name": "лебедев сергей алексеевич",
      "inn": "7806250680",
      "ogrn": "1167847366983",
      "reg_date": "16 сентября 2016 г.",
      "reg_cap": "10 000 руб.",
      "status": null,
      "main_activity": "56.30 подача напитков",
      "main_activity_code": 563000,
      "address": "195027, город санкт-петербург, краснодонская улица, дом 4 лит а, пом 3н"
   },
   {
      "title": "ооо \"мик\"",
      "link": "/id/2203026",
      "head_title": "конкурсный управляющий",
      "head_name": "дмитриев артем анатольевич",
      "inn": "7841345599",
      "ogrn": "5067847430470",
      "reg_date": "10 октября 2006 г.",
      "reg_cap": "115 000 руб.",
      "status": "организация в процессе ликвидации",
      "main_activity": "56.30 подача напитков",
      "main_activity_code": 563000,
      "address": "196247, город санкт-петербург, площадь конституции, дом 2 литер а, помещение 29н"
   },
   {
      "title": "ооо \"максибар\"",
      "link": "/id/10752670",
      "head_title": "директор",
      "head_name": "романова фатима владимировна",
      "inn": "4217180331",
      "ogrn": "1164205080940",
      "reg_date": "8 ноября 2016 г.",
      "reg_cap": "10 000 руб.",
      "status": null,
      "main_activity": "56.30 подача напитков",
      "main_activity_code": 563000,
      "address": "654007, кемеровская область, город новокузнецк, проспект металлургов (центральный р-н), дом 16, помещение 3"
   },
   {
      "title": "ооо \"бар \"скамейка\"",
      "link": "/id/10764594",
      "head_title": "генеральный директор",
      "head_name": "колесников олег вадимович",
      "inn": "7807144645",
      "ogrn": "1167847428561",
      "reg_date": "7 ноября 2016 г.",
      "reg_cap": "10 000 руб.",
      "status": null,
      "main_activity": "56.30 подача напитков",
      "main_activity_code": 563000,
      "address": "198259, город санкт-петербург, проспект ветеранов, дом 155 лит а, помещение 1н"
   },
   {
      "title": "ооо \"орион\"",
      "link": "/id/10909085",
      "head_title": "генеральный директор",
      "head_name": "стрецкул василий васильевич",
      "inn": "2905013480",
      "ogrn": "1172901003010",
      "reg_date": "27 февраля 2017 г.",
      "reg_cap": "100 000 руб.",
      "status": null,
      "main_activity": "56.30 подача напитков",
      "main_activity_code": 563000,
      "address": "197343, город санкт-петербург, улица матроса железняка, дом 57, квартира 505"
   },
   {
      "title": "ооо \"беко\"",
      "link": "/id/10922371",
      "head_title": "генеральный директор",
      "head_name": "белов игорь вячеславович",
      "inn": "7804592374",
      "ogrn": "1177847090728",
      "reg_date": "10 марта 2017 г.",
      "reg_cap": "10 000 руб.",
      "status": null,
      "main_activity": "56.30 подача напитков",
      "main_activity_code": 563000,
      "address": "195197, город санкт-петербург, проспект маршала блюхера, дом 9 корпус 3,литера а, помещение 10-н, офис 1"
   },
   {
      "title": "ооо \"макс микс\"",
      "link": "/id/10932060",
      "head_title": "генеральный директор",
      "head_name": "орловская юлия владимировна",
      "inn": "7814684426",
      "ogrn": "1177847099044",
      "reg_date": "16 марта 2017 г.",
      "reg_cap": "10 000 руб.",
      "status": null,
      "main_activity": "56.30 подача напитков",
      "main_activity_code": 563000,
      "address": "197374, город санкт-петербург, улица савушкина, дом 141 лит. а, офис 616"
   },
   {
      "title": "ооо \"хукастор\"",
      "link": "/id/10947903",
      "head_title": "генеральный директор",
      "head_name": "красильникова мария андреевна",
      "inn": "7806265291",
      "ogrn": "1177847115280",
      "reg_date": "29 марта 2017 г.",
      "reg_cap": "10 000 руб.",
      "status": null,
      "main_activity": "56.30 подача напитков",
      "main_activity_code": 563000,
      "address": "195112, город санкт-петербург, новочеркасский проспект, дом 33 литер а пом 28н"
   },
   {
      "title": "ооо \"гудзь\"",
      "link": "/id/11087442",
      "head_title": "генеральный директор",
      "head_name": "гудзь максим владимирович",
      "inn": "7810699157",
      "ogrn": "1177847243177",
      "reg_date": "14 июля 2017 г.",
      "reg_cap": "30 000 руб.",
      "status": null,
      "main_activity": "56.30 подача напитков",
      "main_activity_code": 563000,
      "address": "196084, город санкт-петербург, воздухоплавательная улица, дом 2 литер д, офис 54д"
   },
   {
      "title": "ооо \"венусто\"",
      "link": "/id/11269535",
      "head_title": "директор",
      "head_name": "черных денис вячеславович",
      "inn": "5260450547",
      "ogrn": "1175275084973",
      "reg_date": "12 декабря 2017 г.",
      "reg_cap": "10 000 руб.",
      "status": null,
      "main_activity": "56.30 подача напитков",
      "main_activity_code": 563000,
      "address": "603163, нижегородская область, город нижний новгород, улица родионова, дом 197, помещение 7"
   },
   {
      "title": "ооо \"паб 13.15\"",
      "link": "/id/11278039",
      "head_title": "генеральный директор",
      "head_name": "михайлова татьяна владимировна",
      "inn": "7704449268",
      "ogrn": "5177746346575",
      "reg_date": "19 декабря 2017 г.",
      "reg_cap": "10 000 руб.",
      "status": null,
      "main_activity": "56.30 подача напитков",
      "main_activity_code": 563000,
      "address": "119021, город москва, комсомольский проспект, дом 14/1 корпус 1, подвал пом. ii комн. 1-19"
   },
   {
      "title": "ооо \"риян\"",
      "link": "/id/11302611",
      "head_title": "генеральный директор",
      "head_name": "борисов евгений владимирович",
      "inn": "7806296941",
      "ogrn": "1187847007072",
      "reg_date": "18 января 2018 г.",
      "reg_cap": "10 000 руб.",
      "status": null,
      "main_activity": "56.30 подача напитков",
      "main_activity_code": 563000,
      "address": "195248, город санкт-петербург, проспект энергетиков, дом 19 литер а, помещение 2"
   },
   {
      "title": "ооо \"фуд энд бевереджес экспресс\"",
      "link": "/id/11340963",
      "head_title": "генеральный директор",
      "head_name": "григорьянц сергей александрович",
      "inn": "7814720515",
      "ogrn": "1187847038796",
      "reg_date": "16 февраля 2018 г.",
      "reg_cap": "100 000 руб.",
      "status": null,
      "main_activity": "56.30 подача напитков",
      "main_activity_code": 563000,
      "address": "197374, город санкт-петербург, мебельная улица, дом 12 корпус 1 литера а, офис 609"
   },
   {
      "title": "ооо гурман2\"",
      "link": "/id/11349563",
      "head_title": "генеральный директор",
      "head_name": "елтышев игорь андреевич",
      "inn": "7804616177",
      "ogrn": "1187847046221",
      "reg_date": "22 февраля 2018 г.",
      "reg_cap": "10 000 руб.",
      "status": null,
      "main_activity": "56.30 подача напитков",
      "main_activity_code": 563000,
      "address": "195220, город санкт-петербург, гжатская улица, дом 22 корпус 2, помещение 6-н"
   },
   {
      "title": "ооо \"портман\"",
      "link": "/id/11439030",
      "head_title": "генеральный директор",
      "head_name": "фомина татьяна всеволодовна",
      "inn": "7814729331",
      "ogrn": "1187847136674",
      "reg_date": "15 мая 2018 г.",
      "reg_cap": "12 000 руб.",
      "status": null,
      "main_activity": "56.30 подача напитков",
      "main_activity_code": 563000,
      "address": "197341, город санкт-петербург, площадь льва мациевича, дом 4, квартира 63"
   },
   {
      "title": "ооо \"бриг\"",
      "link": "/id/11452176",
      "head_title": "генеральный директор",
      "head_name": "орлов антон алексеевич",
      "inn": "7814730552",
      "ogrn": "1187847148521",
      "reg_date": "28 мая 2018 г.",
      "reg_cap": "10 000 руб.",
      "status": null,
      "main_activity": "56.30 подача напитков",
      "main_activity_code": 563000,
      "address": "197350, город санкт-петербург, парашютная улица, дом 52 литер а, квартира 20"
   },
   {
      "title": "ооо \"департамент\"",
      "link": "/id/11532043",
      "head_title": "генеральный директор",
      "head_name": "данилов виталий валерьевич",
      "inn": "7810736708",
      "ogrn": "1187847227424",
      "reg_date": "15 августа 2018 г.",
      "reg_cap": "10 000 руб.",
      "status": null,
      "main_activity": "56.30 подача напитков",
      "main_activity_code": 563000,
      "address": "196211, город санкт-петербург, проспект юрия гагарина, дом 20 корпус 1 литер а, помещение 2-н, офис 4"
   },
   {
      "title": "ооо \"константа\"",
      "link": "/id/11572930",
      "head_title": "генеральный директор",
      "head_name": "константинова светлана евгеньевна",
      "inn": "7806549617",
      "ogrn": "1187847274010",
      "reg_date": "28 сентября 2018 г.",
      "reg_cap": "10 000 руб.",
      "status": null,
      "main_activity": "56.30 подача напитков",
      "main_activity_code": 563000,
      "address": "195067, город санкт-петербург, екатерининский проспект, дом 2 строение 1, помещение 60-н"
   },
   {
      "title": "ооо \"виват\"",
      "link": "/id/11669454",
      "head_title": "директор",
      "head_name": "толстоброва мария андреевна",
      "inn": "1839010668",
      "ogrn": "1191832000051",
      "reg_date": "9 января 2019 г.",
      "reg_cap": "20 000 руб.",
      "status": null,
      "main_activity": "56.30 подача напитков",
      "main_activity_code": 563000,
      "address": "427993, республика удмуртская, город можга, автомобильная улица, дом 17, квартира 2"
   },
   {
      "title": "ооо \"хиггинс групп\"",
      "link": "/id/11694811",
      "head_title": "генеральный директор",
      "head_name": "липицева алена владимировна",
      "inn": "7814752549",
      "ogrn": "1197847027278",
      "reg_date": "8 февраля 2019 г.",
      "reg_cap": "10 000 руб.",
      "status": null,
      "main_activity": "56.30 подача напитков",
      "main_activity_code": 563000,
      "address": "197372, город санкт-петербург, богатырский проспект, дом 25 корпус 1 литер а, помещение 11-н"
   },
   {
      "title": "ооо \"вавилон\"",
      "link": "/id/11733202",
      "head_title": "управляющий - индивидуальный предприниматель",
      "head_name": "голобин сергей владимирович",
      "inn": "7810752795",
      "ogrn": "1197847061060",
      "reg_date": "15 марта 2019 г.",
      "reg_cap": "10 000 руб.",
      "status": null,
      "main_activity": "56.30 подача напитков",
      "main_activity_code": 563000,
      "address": "196158, город санкт-петербург, пулковское шоссе, дом 20 корпус 3 литер а, помещение 17н"
   },
   {
      "title": "ооо \"инрекон\"",
      "link": "/id/955780",
      "head_title": "директор",
      "head_name": "мазалова галина павловна",
      "inn": "2222032208",
      "ogrn": "1022201133503",
      "reg_date": "28 июня 2001 г.",
      "reg_cap": "10 000 руб.",
      "status": null,
      "main_activity": "56.30 подача напитков",
      "main_activity_code": 563000,
      "address": "656000, алтайский край, город барнаул, взлетная улица, 57"
   },
   {
      "title": "ооо \"светлана\"",
      "link": "/id/628836",
      "head_title": "директор",
      "head_name": "прошунина светлана михайловна",
      "inn": "6166013083",
      "ogrn": "1026104032558",
      "reg_date": "16 февраля 1994 г.",
      "reg_cap": "10 000 руб.",
      "status": null,
      "main_activity": "56.30 подача напитков",
      "main_activity_code": 563000,
      "address": "344029, ростовская область, город ростов-на-дону, проспект шолохова, 123/2а/8"
   },
   {
      "title": "ооо \"декор\"",
      "link": "/id/4457654",
      "head_title": "генеральный директор",
      "head_name": "бережной георгий зурабович",
      "inn": "7808033240",
      "ogrn": "1037843003296",
      "reg_date": "5 октября 1999 г.",
      "reg_cap": "12 000 руб.",
      "status": null,
      "main_activity": "56.30 подача напитков",
      "main_activity_code": 563000,
      "address": "197739, город санкт-петербург, поселок солнечное, приморское шоссе, дом 376а лит. а"
   },
   {
      "title": "ооо \"аллис\"",
      "link": "/id/4406953",
      "head_title": "директор",
      "head_name": "шестминцев андрей юрьевич",
      "inn": "6672181140",
      "ogrn": "1056604390160",
      "reg_date": "11 февраля 2005 г.",
      "reg_cap": "10 000 руб.",
      "status": null,
      "main_activity": "56.30 подача напитков",
      "main_activity_code": 563000,
      "address": "620138, свердловская область, город екатеринбург, байкальская улица, 37, 16"
   },
   {
      "title": "ооо \"победа\"",
      "link": "/id/2548309",
      "head_title": "директор",
      "head_name": "токтеева инна константиновна",
      "inn": "4345132608",
      "ogrn": "1064345095770",
      "reg_date": "14 апреля 2006 г.",
      "reg_cap": "10 000 руб.",
      "status": null,
      "main_activity": "56.30 подача напитков",
      "main_activity_code": 563000,
      "address": "610000, кировская область, город киров, улица володарского, 103 а"
   },
   {
      "title": "ооо \"вездеходофф\"",
      "link": "/id/1084468",
      "head_title": "директор",
      "head_name": "кравченко руслан григорьевич",
      "inn": "7017150840",
      "ogrn": "1067017157998",
      "reg_date": "19 июня 2006 г.",
      "reg_cap": "10 000 руб.",
      "status": null,
      "main_activity": "56.30 подача напитков",
      "main_activity_code": 563000,
      "address": "634012, томская область, город томск, киевская улица, 9, 285"
   },
   {
      "title": "ооо \"ивентус\"",
      "link": "/id/2283450",
      "head_title": "генеральный директор",
      "head_name": "драгункин геннадий владимирович",
      "inn": "7805442131",
      "ogrn": "1077847634798",
      "reg_date": "15 октября 2007 г.",
      "reg_cap": "10 000 руб.",
      "status": null,
      "main_activity": "56.30 подача напитков",
      "main_activity_code": 563000,
      "address": "191186, город санкт-петербург, набережная канала грибоедова, дом 26 литер а, помещение 8-н каб.3"
   },
   {
      "title": "ооо \"снабс\"",
      "link": "/id/607876",
      "head_title": "руководитель ликвидационной комиссии",
      "head_name": "росочинский константин константинович",
      "inn": "8602061654",
      "ogrn": "1078602007945",
      "reg_date": "24 июля 2007 г.",
      "reg_cap": "10 000 руб.",
      "status": "организация в процессе ликвидации",
      "main_activity": "56.30 подача напитков",
      "main_activity_code": 563000,
      "address": "628406, ханты-мансийский автономный округ - югра, город сургут, университетская улица, 7, 150"
   },
   {
      "title": "ооо \"скрыня\"",
      "link": "/id/6051164",
      "head_title": "генеральный директор",
      "head_name": "дмитриева наталья владимировна",
      "inn": "7843314571",
      "ogrn": "1127847165093",
      "reg_date": "2 апреля 2012 г.",
      "reg_cap": "10 000 руб.",
      "status": null,
      "main_activity": "56.30 подача напитков",
      "main_activity_code": 563000,
      "address": "197706, город санкт-петербург, город сестрорецк, улица володарского, 14, помещение 1 2 3 4 5 6 10 11 12"
   },
   {
      "title": "ооо \"народный дискаунт\"",
      "link": "/id/6079877",
      "head_title": "генеральный директор",
      "head_name": "купцов матвей владимирович",
      "inn": "7811521494",
      "ogrn": "1127847258296",
      "reg_date": "10 мая 2012 г.",
      "reg_cap": "10 000 руб.",
      "status": null,
      "main_activity": "56.30 подача напитков",
      "main_activity_code": 563000,
      "address": "198099, город санкт-петербург, промышленная улица, дом 6 литера а, помещение 3-н"
   },
   {
      "title": "ооо \"новый формат\"",
      "link": "/id/7821028",
      "head_title": "генеральный директор",
      "head_name": "шахов андрей александрович",
      "inn": "2320233216",
      "ogrn": "1152366007969",
      "reg_date": "15 сентября 2015 г.",
      "reg_cap": "10 000 руб.",
      "status": null,
      "main_activity": "56.30 подача напитков",
      "main_activity_code": 563000,
      "address": "354068, краснодарский край, город сочи, калужская улица, дом 10, квартира 2"
   },
   {
      "title": "ооо \"лофт компани\"",
      "link": "/id/7449846",
      "head_title": "ликвидатор",
      "head_name": "вистунова евгения николаевна",
      "inn": "5503119971",
      "ogrn": "1155543004583",
      "reg_date": "12 февраля 2015 г.",
      "reg_cap": "10 000 руб.",
      "status": "организация в процессе ликвидации",
      "main_activity": "56.30 подача напитков",
      "main_activity_code": 563000,
      "address": "644060, омская область, город омск, улица гуртьева, дом 19, квартира 54"
   },
   {
      "title": "ооо \"паддингтон\"",
      "link": "/id/7900769",
      "head_title": "генеральный директор",
      "head_name": "горбачев владислав владиславович",
      "inn": "7736254832",
      "ogrn": "1157746982744",
      "reg_date": "26 октября 2015 г.",
      "reg_cap": "30 000 руб.",
      "status": null,
      "main_activity": "56.30 подача напитков",
      "main_activity_code": 563000,
      "address": "119334, город москва, улица косыгина, дом 15"
   },
   {
      "title": "ооо \"спортивные системы\"",
      "link": "/id/7637863",
      "head_title": "генеральный директор",
      "head_name": "хурсандкулов зиедулло кутфидинович",
      "inn": "7805312492",
      "ogrn": "1157847137832",
      "reg_date": "16 апреля 2015 г.",
      "reg_cap": "10 000 руб.",
      "status": null,
      "main_activity": "56.30 подача напитков",
      "main_activity_code": 563000,
      "address": "198095, город санкт-петербург, тракторная улица, дом 13 литер а, помещение 17-н"
   },
   {
      "title": "ооо \"лакикловер\"",
      "link": "/id/10505690",
      "head_title": "генеральный директор",
      "head_name": "содикова маирамхон",
      "inn": "7708292836",
      "ogrn": "1167746549068",
      "reg_date": "8 июня 2016 г.",
      "reg_cap": "22 000 руб.",
      "status": null,
      "main_activity": "56.30 подача напитков",
      "main_activity_code": 563000,
      "address": "107045, город москва, площадь сухаревская б., дом 14/7"
   },
   {
      "title": "ооо \"максимум\"",
      "link": "/id/11083091",
      "head_title": "генеральный директор",
      "head_name": "каряка алексей александрович",
      "inn": "5406977967",
      "ogrn": "1175476076929",
      "reg_date": "10 июля 2017 г.",
      "reg_cap": "10 000 руб.",
      "status": null,
      "main_activity": "56.30 подача напитков",
      "main_activity_code": 563000,
      "address": "630099, новосибирская область, город новосибирск, советская улица, дом 18, офис 339"
   },
   {
      "title": "ооо \"капиталъ\"",
      "link": "/id/11584898",
      "head_title": "генеральный директор",
      "head_name": "павленко татьяна викторовна",
      "inn": "6161086095",
      "ogrn": "1186196043340",
      "reg_date": "12 октября 2018 г.",
      "reg_cap": "10 000 руб.",
      "status": null,
      "main_activity": "56.30 подача напитков",
      "main_activity_code": 563000,
      "address": "344092, ростовская область, город ростов-на-дону, улица добровольского, дом 6а, офис 1"
   },
   {
      "title": "ооо \"территория\"",
      "link": "/id/11712397",
      "head_title": "директор",
      "head_name": "скачков валерий михайлович",
      "inn": "1651084193",
      "ogrn": "1191690017420",
      "reg_date": "21 февраля 2019 г.",
      "reg_cap": "10 000 руб.",
      "status": null,
      "main_activity": "56.30 подача напитков",
      "main_activity_code": 563000,
      "address": "423578, республика татарстан, нижнекамский район, город нижнекамск, улица юности, дом 12 помещение 1010, комната 88"
   },
   {
      "title": "ооо \"степанов и амелин\"",
      "link": "/id/11725744",
      "head_title": "генеральный директор",
      "head_name": "степанов никита алексеевич",
      "inn": "7805745175",
      "ogrn": "1197847053690",
      "reg_date": "7 марта 2019 г.",
      "reg_cap": "10 000 руб.",
      "status": null,
      "main_activity": "56.30 подача напитков",
      "main_activity_code": 563000,
      "address": "198260, город санкт-петербург, улица солдата корзуна, дом 50 литер а, квартира 48"
   },
   {
      "title": "ооо \"триумф\"",
      "link": "/id/11753965",
      "head_title": "директор",
      "head_name": "басенкина юлия сергеевна",
      "inn": "4329019958",
      "ogrn": "1194350004155",
      "reg_date": "4 апреля 2019 г.",
      "reg_cap": "10 000 руб.",
      "status": null,
      "main_activity": "56.30 подача напитков",
      "main_activity_code": 563000,
      "address": "613150, кировская область, слободской район, город слободской, улица герцена, дом 77"
   },
   {
      "title": "ооо \"мария\"",
      "link": "/id/3872901",
      "head_title": "генеральный директор",
      "head_name": "котова мария николаевна",
      "inn": "5835075534",
      "ogrn": "1085835000790",
      "reg_date": "29 февраля 2008 г.",
      "reg_cap": "11 000 руб.",
      "status": null,
      "main_activity": "56.30 подача напитков",
      "main_activity_code": 563000,
      "address": "440071, пензенская область, город пенза, ладожская улица, дом 37а"
   },
   {
      "title": "ооо \"спектр-2\"",
      "link": "/id/267749",
      "head_title": "директор",
      "head_name": "назаров вячеслав вадимович",
      "inn": "7810269901",
      "ogrn": "1027804852680",
      "reg_date": "3 сентября 2002 г.",
      "reg_cap": "20 000 руб.",
      "status": null,
      "main_activity": "56.30 подача напитков",
      "main_activity_code": 563000,
      "address": "117534, город москва, кировоградская улица, 23а-1"
   },
   {
      "title": "ооо \"джэм холл-2\"",
      "link": "/id/2028665",
      "head_title": "генеральный директор",
      "head_name": "кондратенко вадим валерьянович",
      "inn": "7810205457",
      "ogrn": "1037821035658",
      "reg_date": "20 сентября 2000 г.",
      "reg_cap": "16 000 руб.",
      "status": null,
      "main_activity": "56.30 подача напитков",
      "main_activity_code": 563000,
      "address": "191036, город санкт-петербург, невский проспект, дом 130 литер а, помещение 14-н"
   },
   {
      "title": "ооо \"нева-холод\"",
      "link": "/id/2639080",
      "head_title": "генеральный директор",
      "head_name": "мусаев руслан шахсоварович",
      "inn": "7813054446",
      "ogrn": "1037828004345",
      "reg_date": "20 января 1994 г.",
      "reg_cap": "15 000 руб.",
      "status": null,
      "main_activity": "56.30 подача напитков",
      "main_activity_code": 563000,
      "address": "197136, город санкт-петербург, лахтинская улица, 11"
   },
   {
      "title": "ооо \"грин\"",
      "link": "/id/3770031",
      "head_title": "генеральный директор",
      "head_name": "кондратенко вадим валерьянович",
      "inn": "7813160807",
      "ogrn": "1037828014619",
      "reg_date": "20 февраля 2002 г.",
      "reg_cap": "10 000 руб.",
      "status": null,
      "main_activity": "56.30 подача напитков",
      "main_activity_code": 563000,
      "address": "191036, город санкт-петербург, невский проспект, дом 130 литер а, помещение 14-н"
   },
   {
      "title": "ооо \"грэй\"",
      "link": "/id/2366002",
      "head_title": "генеральный директор",
      "head_name": "кондратенко вадим валерьянович",
      "inn": "7813160412",
      "ogrn": "1037828014641",
      "reg_date": "20 февраля 2002 г.",
      "reg_cap": "10 000 руб.",
      "status": null,
      "main_activity": "56.30 подача напитков",
      "main_activity_code": 563000,
      "address": "191036, город санкт-петербург, невский проспект, дом 130 литер а, помещение 14-н"
   },
   {
      "title": "ооо \"грот\"",
      "link": "/id/2291953",
      "head_title": "генеральный директор",
      "head_name": "соколов виктор сергеевич",
      "inn": "7813340013",
      "ogrn": "1067847263021",
      "reg_date": "13 февраля 2006 г.",
      "reg_cap": "10 000 руб.",
      "status": null,
      "main_activity": "56.30 подача напитков",
      "main_activity_code": 563000,
      "address": "197136, город санкт-петербург, ординарная улица, 18 лит.а, пом.6н"
   },
   {
      "title": "ооо \"сакартвело\"",
      "link": "/id/1460090",
      "head_title": "ликвидатор",
      "head_name": "боджгуа майя пантелеймоновна",
      "inn": "7813368266",
      "ogrn": "1077847000285",
      "reg_date": "6 февраля 2007 г.",
      "reg_cap": "10 000 руб.",
      "status": "организация в процессе ликвидации",
      "main_activity": "56.30 подача напитков",
      "main_activity_code": 563000,
      "address": "199178, город санкт-петербург, линия 12-я в.о., 13 литер ап, помещение 12-н"
   },
   {
      "title": "ооо \"фрэш\"",
      "link": "/id/3057658",
      "head_title": "генеральный директор",
      "head_name": "рзагулиев назим селим оглы",
      "inn": "7841401772",
      "ogrn": "1097847002230",
      "reg_date": "14 января 2009 г.",
      "reg_cap": "10 000 руб.",
      "status": null,
      "main_activity": "56.30 подача напитков",
      "main_activity_code": 563000,
      "address": "197022, город санкт-петербург, каменноостровский проспект, 42"
   },
   {
      "title": "ооо \"культурный центр \"петроградец\"",
      "link": "/id/5559337",
      "head_title": "генеральный директор",
      "head_name": "коротких ксения владимировна",
      "inn": "7813506533",
      "ogrn": "1117847282090",
      "reg_date": "12 июля 2011 г.",
      "reg_cap": "10 000 руб.",
      "status": null,
      "main_activity": "56.30 подача напитков",
      "main_activity_code": 563000,
      "address": "191036, город санкт-петербург, лиговский проспект, дом 33-35 литер а, помещение 8н"
   },
   {
      "title": "ооо \"солнце\"",
      "link": "/id/5979609",
      "head_title": "генеральный директор",
      "head_name": "савельев игорь анатольевич",
      "inn": "7813529570",
      "ogrn": "1127847144347",
      "reg_date": "22 марта 2012 г.",
      "reg_cap": "10 000 руб.",
      "status": null,
      "main_activity": "56.30 подача напитков",
      "main_activity_code": 563000,
      "address": "197198, город санкт-петербург, проспект добролюбова, 7/2, помещение 19-н"
   },
   {
      "title": "ооо \"средний класс\"",
      "link": "/id/6115138",
      "head_title": "генеральный директор",
      "head_name": "фрумкин осип борисович",
      "inn": "7813538172",
      "ogrn": "1127847347847",
      "reg_date": "29 июня 2012 г.",
      "reg_cap": "20 000 руб.",
      "status": null,
      "main_activity": "56.30 подача напитков",
      "main_activity_code": 563000,
      "address": "191014, город санкт-петербург, литейный проспект, дом 55 литер а, помещение 2н"
   },
   {
      "title": "ооо \"большой дискаунт\"",
      "link": "/id/6813354",
      "head_title": "генеральный директор",
      "head_name": "купцов матвей владимирович",
      "inn": "7813557496",
      "ogrn": "1137847095517",
      "reg_date": "5 марта 2013 г.",
      "reg_cap": "10 000 руб.",
      "status": null,
      "main_activity": "56.30 подача напитков",
      "main_activity_code": 563000,
      "address": "197022, город санкт-петербург, проспект большой п.с., 79 лит. а, пом. 1н"
   },
   {
      "title": "ооо \"норд\"",
      "link": "/id/7408611",
      "head_title": "генеральный директор",
      "head_name": "богачев андрей васильевич",
      "inn": "7816559445",
      "ogrn": "1137847130805",
      "reg_date": "29 марта 2013 г.",
      "reg_cap": "10 000 руб.",
      "status": null,
      "main_activity": "56.30 подача напитков",
      "main_activity_code": 563000,
      "address": "197022, город санкт-петербург, улица профессора попова, дом 47 литер а, помещение 53"
   },
   {
      "title": "ооо \"асм\"",
      "link": "/id/6981419",
      "head_title": "директор",
      "head_name": "колесников юрий константинович",
      "inn": "7802836804",
      "ogrn": "1137847341378",
      "reg_date": "11 сентября 2013 г.",
      "reg_cap": "12 000 руб.",
      "status": null,
      "main_activity": "56.30 подача напитков",
      "main_activity_code": 563000,
      "address": "197198, город санкт-петербург, татарский переулок, дом 4 литер а, помещение 6н, комната no1"
   },
   {
      "title": "ооо \"аперитиво\"",
      "link": "/id/7047088",
      "head_title": "генеральный директор",
      "head_name": "наумов константин михайлович",
      "inn": "7840497616",
      "ogrn": "1137847432568",
      "reg_date": "11 ноября 2013 г.",
      "reg_cap": "50 000 руб.",
      "status": null,
      "main_activity": "56.30 подача напитков",
      "main_activity_code": 563000,
      "address": "197198, город санкт-петербург, кронверкский проспект, дом 65 литер а, помещение 1-н"
   },
   {
      "title": "ооо \"фитнесбар коктейль\"",
      "link": "/id/7172183",
      "head_title": "генеральный директор",
      "head_name": "лукашевич диляра рафаиловна",
      "inn": "7813581805",
      "ogrn": "1147847051780",
      "reg_date": "13 февраля 2014 г.",
      "reg_cap": "10 000 руб.",
      "status": null,
      "main_activity": "56.30 подача напитков",
      "main_activity_code": 563000,
      "address": "197110, город санкт-петербург, крестовский проспект, дом 24 б"
   },
   {
      "title": "ооо \"имбайб\"",
      "link": "/id/9586011",
      "head_title": "директор",
      "head_name": "козлова ирина юрьевна",
      "inn": "7813600536",
      "ogrn": "1147847372155",
      "reg_date": "24 октября 2014 г.",
      "reg_cap": "10 000 руб.",
      "status": null,
      "main_activity": "56.30 подача напитков",
      "main_activity_code": 563000,
      "address": "191014, город санкт-петербург, улица жуковского, дом 6 лит. а, пом. 11н"
   },
   {
      "title": "ооо \"счастье на петроградке\"",
      "link": "/id/7631188",
      "head_title": "генеральный директор",
      "head_name": "головина елена сергеевна",
      "inn": "7813219779",
      "ogrn": "1157847141627",
      "reg_date": "20 апреля 2015 г.",
      "reg_cap": "10 000 руб.",
      "status": null,
      "main_activity": "56.30 подача напитков",
      "main_activity_code": 563000,
      "address": "197136, город санкт-петербург, проспект большой п.с., дом 88 литер а, пом 2н"
   },
   {
      "title": "ооо \"сладкие подарки\"",
      "link": "/id/7617898",
      "head_title": "генеральный директор",
      "head_name": "карпова наталия евгеньевна",
      "inn": "7801279117",
      "ogrn": "1157847149965",
      "reg_date": "24 апреля 2015 г.",
      "reg_cap": "10 000 руб.",
      "status": null,
      "main_activity": "56.30 подача напитков",
      "main_activity_code": 563000,
      "address": "197110, город санкт-петербург, чкаловский проспект, дом 15 литера а, помещение 120"
   },
   {
      "title": "ооо \"лавка счастья\"",
      "link": "/id/7652976",
      "head_title": "генеральный директор",
      "head_name": "карпова наталия евгеньевна",
      "inn": "7801279854",
      "ogrn": "1157847162516",
      "reg_date": "7 мая 2015 г.",
      "reg_cap": "10 000 руб.",
      "status": null,
      "main_activity": "56.30 подача напитков",
      "main_activity_code": 563000,
      "address": "197110, город санкт-петербург, чкаловский проспект, дом 15 литера а, помещение 120"
   },
   {
      "title": "ооо \"экошот\"",
      "link": "/id/7764231",
      "head_title": "генеральный директор",
      "head_name": "карпов даниил александрович",
      "inn": "7813227579",
      "ogrn": "1157847264673",
      "reg_date": "3 августа 2015 г.",
      "reg_cap": "10 000 руб.",
      "status": null,
      "main_activity": "56.30 подача напитков",
      "main_activity_code": 563000,
      "address": "197198, город санкт-петербург, большая пушкарская улица, дом 42/16 корпус литер а, помещение 1-н"
   },
   {
      "title": "ооо \"прожектор\"",
      "link": "/id/10719452",
      "head_title": "директор",
      "head_name": "карпухина яна викторовна",
      "inn": "2364014606",
      "ogrn": "1162364051321",
      "reg_date": "20 октября 2016 г.",
      "reg_cap": "10 000 руб.",
      "status": null,
      "main_activity": "56.30 подача напитков",
      "main_activity_code": 563000,
      "address": "352396, краснодарский край, кавказский район, город кропоткин, двойная улица, дом 144/3"
   },
   {
      "title": "ооо \"четверг\"",
      "link": "/id/10440165",
      "head_title": "генеральный директор",
      "head_name": "ершов владислав валерьевич",
      "inn": "7813249580",
      "ogrn": "1167847184625",
      "reg_date": "14 апреля 2016 г.",
      "reg_cap": "10 000 руб.",
      "status": null,
      "main_activity": "56.30 подача напитков",
      "main_activity_code": 563000,
      "address": "197136, город санкт-петербург, улица подрезова, дом 17 литера а, помещение 4н"
   },
   {
      "title": "ооо \"а2 клуб\"",
      "link": "/id/10727066",
      "head_title": "генеральный директор",
      "head_name": "агузарова альбина алибековна",
      "inn": "7813263168",
      "ogrn": "1167847408651",
      "reg_date": "20 октября 2016 г.",
      "reg_cap": "1 000 000 руб.",
      "status": null,
      "main_activity": "56.30 подача напитков",
      "main_activity_code": 563000,
      "address": "197022, город санкт-петербург, проспект медиков, дом 3 литер а, помещение 1н"
   },
   {
      "title": "ооо \"ск \"жилпромстрой\"",
      "link": "/id/10879267",
      "head_title": "генеральный директор",
      "head_name": "шнейдер мария александровна",
      "inn": "7813271183",
      "ogrn": "1177847051062",
      "reg_date": "8 февраля 2017 г.",
      "reg_cap": "10 000 руб.",
      "status": null,
      "main_activity": "56.30 подача напитков",
      "main_activity_code": 563000,
      "address": "191002, город санкт-петербург, разъезжая улица, дом 7 литер а, помещение 3н"
   },
   {
      "title": "ооо \"победа\"",
      "link": "/id/11196709",
      "head_title": "генеральный директор",
      "head_name": "братушка артем андреевич",
      "inn": "7813289342",
      "ogrn": "1177847331001",
      "reg_date": "10 октября 2017 г.",
      "reg_cap": "10 000 руб.",
      "status": null,
      "main_activity": "56.30 подача напитков",
      "main_activity_code": 563000,
      "address": "197198, город санкт-петербург, красносельская улица, дом 16 литер а, помещение 7н"
   },
   {
      "title": "ооо \"маслоу бар\"",
      "link": "/id/11406779",
      "head_title": "генеральный директор",
      "head_name": "масленникова марина альбертовна",
      "inn": "7813610189",
      "ogrn": "1187847102189",
      "reg_date": "10 апреля 2018 г.",
      "reg_cap": "50 000 руб.",
      "status": null,
      "main_activity": "56.30 подача напитков",
      "main_activity_code": 563000,
      "address": "197198, город санкт-петербург, проспект большой п.с., дом 27/1 литер а, квартира 19"
   },
   {
      "title": "ооо \"на набережной\"",
      "link": "/id/11468077",
      "head_title": "генеральный директор",
      "head_name": "козлова елена николаевна",
      "inn": "7813613729",
      "ogrn": "1187847163459",
      "reg_date": "9 июня 2018 г.",
      "reg_cap": "10 000 руб.",
      "status": null,
      "main_activity": "56.30 подача напитков",
      "main_activity_code": 563000,
      "address": "197198, город санкт-петербург, съезжинская улица, дом 19 литер а, помещение 3-н офис 3г"
   },
   {
      "title": "ооо \"ника групп\"",
      "link": "/id/11511860",
      "head_title": "генеральный директор",
      "head_name": "василенко евгений вячеславович",
      "inn": "7813616208",
      "ogrn": "1187847208834",
      "reg_date": "25 июля 2018 г.",
      "reg_cap": "10 000 руб.",
      "status": null,
      "main_activity": "56.30 подача напитков",
      "main_activity_code": 563000,
      "address": "197198, город санкт-петербург, ропшинская улица, дом 4 литер а, пом. 1н"
   },
   {
      "title": "ооо \"дегустатор\"",
      "link": "/id/11549303",
      "head_title": "генеральный директор",
      "head_name": "молев дмитрий владимирович",
      "inn": "7813619311",
      "ogrn": "1187847248863",
      "reg_date": "6 сентября 2018 г.",
      "reg_cap": "60 000 руб.",
      "status": null,
      "main_activity": "56.30 подача напитков",
      "main_activity_code": 563000,
      "address": "197101, город санкт-петербург, проспект большой п.с., дом 63 литер б, помещение 1н"
   },
   {
      "title": "ооо \"пин78\"",
      "link": "/id/11651723",
      "head_title": "генеральный директор",
      "head_name": "порошин игорь николаевич",
      "inn": "7813628323",
      "ogrn": "1187847377948",
      "reg_date": "16 декабря 2018 г.",
      "reg_cap": "10 000 руб.",
      "status": null,
      "main_activity": "56.30 подача напитков",
      "main_activity_code": 563000,
      "address": "197101, город санкт-петербург, улица мира, дом 25 литер а, помещение 5н"
   },
   {
      "title": "ооо \"хмель\"",
      "link": "/id/11750225",
      "head_title": "директор",
      "head_name": "казаков алексей олегович",
      "inn": "2724233765",
      "ogrn": "1192724007300",
      "reg_date": "2 апреля 2019 г.",
      "reg_cap": "10 000 руб.",
      "status": null,
      "main_activity": "56.30 подача напитков",
      "main_activity_code": 563000,
      "address": "680031, хабаровский край, город хабаровск, улица карла маркса, дом 147, квартира 107"
   },
   {
      "title": "ооо \"галактика\"",
      "link": "/id/1920255",
      "head_title": "директор",
      "head_name": "фролова светлана федоровна",
      "inn": "2127314273",
      "ogrn": "1022100975731",
      "reg_date": "22 февраля 2001 г.",
      "reg_cap": null,
      "status": null,
      "main_activity": "56.30 подача напитков",
      "main_activity_code": 563000,
      "address": "428000, чувашская республика - чувашия, город чебоксары, проспект мира, дом 7, офис 1"
   },
   {
      "title": "ооо \"гэлакси\"",
      "link": "/id/1295199",
      "head_title": "директор",
      "head_name": "фролова светлана федоровна",
      "inn": "2127328830",
      "ogrn": "1032127017955",
      "reg_date": "26 декабря 2003 г.",
      "reg_cap": "10 000 руб.",
      "status": null,
      "main_activity": "56.30 подача напитков",
      "main_activity_code": 563000,
      "address": "428000, чувашская республика - чувашия, город чебоксары, проспект мира, дом 7, офис 1"
   },
   {
      "title": "ооо \"система\"",
      "link": "/id/4119966",
      "head_title": "директор",
      "head_name": "белик георгий игоревич",
      "inn": "2801107038",
      "ogrn": "1052800101496",
      "reg_date": "15 ноября 2005 г.",
      "reg_cap": "1 000 000 руб.",
      "status": null,
      "main_activity": "56.30 подача напитков",
      "main_activity_code": 563000,
      "address": "675000, амурская область, город благовещенск, улица ленина, дом 29 корпус 37"
   },
   {
      "title": "ооо \"белый дом\"",
      "link": "/id/3029081",
      "head_title": "директор",
      "head_name": "куликова лариса владимировна",
      "inn": "5010033004",
      "ogrn": "1055001816650",
      "reg_date": "22 декабря 2005 г.",
      "reg_cap": "10 000 руб.",
      "status": null,
      "main_activity": "56.30 подача напитков",
      "main_activity_code": 563000,
      "address": "141981, московская область, город дубна, проспект боголюбова, 46"
   },
   {
      "title": "ооо \"рона\"",
      "link": "/id/2319659",
      "head_title": "директор",
      "head_name": "зверев роман леонидович",
      "inn": "5042104219",
      "ogrn": "1085038015105",
      "reg_date": "1 декабря 2008 г.",
      "reg_cap": "10 000 руб.",
      "status": null,
      "main_activity": "56.30 подача напитков",
      "main_activity_code": 563000,
      "address": "141371, московская область, сергиево-посадский район, город хотьково, улица михеенко, 24"
   }
]